{
  "id": 22,
  "slug": "deployment",
  "stage": 3,
  "title": "部署 + Docker",
  "subtitle": "Docker / Railway / Fly.io",
  "icon": "container",
  "description": "部署 + Docker：Docker / Railway / Fly.io",
  "status": "published",
  "difficulty": "intermediate",
  "prerequisites": [
    16,
    20
  ],
  "estimatedHours": 12,
  "outcomes": [
    "理解核心概念",
    "實作主流工具",
    "整章實戰可發佈作品",
    "知道生態 / 接案行情",
    "對齊 2026 業界主流"
  ],
  "lessons": [
    {
      "title": "部署總圖：從 dev 到 production",
      "oneLineSummary": "寫完 code → user 用到、中間有 10 個關卡",
      "analogy": "懂部署 = Senior 工程師。",
      "content": "**部署（Deploy）= 把你的程式從「自己電腦」搬到「網路上其他人也能用」**。**世界上一半工程師卡在這關**——code 寫得很好、但不會把它放到線上。\n\n> 💡 **這課的價值**：先把整個部署地圖印在腦袋裡——dev → build → artifact → runtime → 監控。之後每一課你會知道自己在哪一段。\n\n  \n### 1. 部署「從電腦到全世界」的 5 個階段\n\n![Zeabur / Vercel 部署流程（一）：連 GitHub → 設 env](/lesson-img/ch22/ch22_deploy_zeabur1.png)\n\n![Zeabur / Vercel 部署流程（二）：deploy 上線](/lesson-img/ch22/ch22_deploy_zeabur2.png)\n\n\n```text\n🟢 Stage 1：Dev（開發）\n   - 你電腦上跑（localhost:3000）\n   - 只有你看得到\n\n🟡 Stage 2：Build（建置）\n   - source code → 可執行的 artifact\n   - 編譯 / 打包 / 壓縮\n   - 例：tsc → .js、npm run build → dist/\n\n🔵 Stage 3：Artifact（產物）\n   - 一份「打包好的程式」\n   - 可以是：tarball、Docker image、static folder\n   - 存到 Container Registry / S3\n\n🟣 Stage 4：Runtime（執行環境）\n   - 真正在跑的機器\n   - VM / Container / Serverless / Edge\n\n🔴 Stage 5：監控 + 維運\n   - log / metric / alert\n   - 出事要知道 + 救得回來\n```\n\n  \n### 2. 6 種 deploy 方式（演進史）\n\n```text\n1990s  傳統 server\n       自己買機器、放機房\n\n2006   AWS EC2 = 虛擬機（VM）\n       租 AWS 的機器、自己裝\n\n2010s  PaaS（Heroku）\n       push code、Heroku 跑全部\n       不用管 OS\n\n2014   Docker = container\n       打包 OS + 程式、到處都能跑\n\n2015   Kubernetes（k8s）\n       管很多 container\n\n2018   Serverless（Vercel / Lambda）\n       連 server 都不用管\n       上 code、按用量算錢\n\n2020s  Edge Compute（Cloudflare Workers）\n       跑在離使用者最近的機器\n```\n\n  \n### 3. 環境（Environment）— 至少 3 套\n\n```text\n🟢 Dev（local）\n   你電腦\n   - 假資料\n   - 隨便壞\n   - 快速 iterate\n\n🟡 Staging / Preview\n   仿正式的測試環境\n   - 用真資料 sample\n   - PR 自動部署\n   - 給 QA / PM 測\n\n🔴 Production（線上）\n   真正服務客戶\n   - 真資料、真錢\n   - 不能掛\n   - 不能隨便改\n```\n\n**有些公司**還會加：\n- `Dev` → `Test` → `UAT` → `Pre-prod` → `Prod`（金融常見、5 層）\n- `Canary`（先給 1% 流量試）\n\n  \n### 4. 12-Factor App — 經典原則\n\nHeroku 提出、業界公認最佳實踐：\n\n```text\n1. Codebase    一個 repo\n2. Dependencies 明確宣告（package.json / requirements.txt）\n3. Config      環境變數、不寫死\n4. Backing Services 把 DB / Redis 當資源\n5. Build / Release / Run  三階段分離\n6. Processes   無狀態\n7. Port binding 自帶 web server\n8. Concurrency 用 process 模型擴展\n9. Disposability 啟動快、優雅關閉\n10. Dev / Prod parity  環境差異小\n11. Logs       stdout（不寫檔案）\n12. Admin processes 一次性 script 跟 app 一起\n```\n\n**白話**：每條都是被「半夜叫醒救機」的工程師寫的血淚教訓。\n\n  \n### 5. CI / CD — 自動化部署\n\n```text\nCI（Continuous Integration、持續整合）\n   - push code → 自動跑 test / lint / build\n   - 確認沒爆\n\nCD（Continuous Deployment、持續部署）\n   - test 過 → 自動 deploy\n   - 不用人按按鈕\n```\n\n📄 **完整流程**：\n\n```text\n1. 工程師 push code 到 PR branch\n2. GitHub Actions 觸發：\n   - lint\n   - typecheck\n   - test\n   - build\n   - 部署到 Preview URL\n3. PR review pass\n4. merge 到 main\n5. GitHub Actions：\n   - 再跑一次 test\n   - build production artifact\n   - 部署到 staging\n   - 跑 smoke test\n   - 部署到 production\n   - 通知 Slack「上線了」\n```\n\n  \n### 6. 4 種 runtime 取捨\n\n```text\n🟢 PaaS（Vercel / Railway / Render）\n   ✅ 零設定、push 就跑\n   ✅ 自動 HTTPS / CDN / Preview\n   ❌ 鎖死平台、貴\n   適合：90% web app\n\n🔵 Container（Docker / k8s）\n   ✅ 控制權最大\n   ✅ 任何雲都能跑\n   ❌ 要會寫 Dockerfile / yaml\n   適合：中大型、多 service\n\n🟣 Serverless（Lambda / Cloudflare Workers）\n   ✅ 按量計費、自動 scale\n   ✅ 沒 idle 成本\n   ❌ cold start\n   ❌ 執行時間有限（Lambda 15 分鐘）\n   適合：API / 偶爾跑的任務\n\n🟡 VM（EC2 / GCE / DigitalOcean Droplet）\n   ✅ 最便宜（大量時）\n   ✅ 最自由\n   ❌ 自己裝、自己 patch\n   適合：成本敏感、特殊需求\n```\n\n  \n### 7. 監控（Observability、可觀測性）\n\n```text\n📊 Metrics（指標）\n   - 數字：QPS、延遲、CPU、記憶體\n   - 工具：Prometheus、Grafana、DataDog\n\n📜 Logs（日誌）\n   - 文字：每個 request、每個 error\n   - 工具：CloudWatch、Loki、Logtail\n\n🔍 Traces（追蹤）\n   - request 在多個 service 間的旅程\n   - 工具：OpenTelemetry、Jaeger、Honeycomb\n\n🚨 Alerts（警報）\n   - 出事打電話 / 發 Slack\n   - 工具：PagerDuty、Opsgenie\n```\n\n  \n### 8. 5 大常見坑\n\n```text\n❌ 1. 沒有 staging、直接 deploy production\n   → 一推上線就壞、客戶看到\n   → 修：永遠 staging 先\n\n❌ 2. config 寫死在 code 裡\n   → API key / DB URL 都 hardcode\n   → 修：用環境變數、機密管理\n\n❌ 3. 沒 CI/CD、手動 deploy\n   → 每次都漏步驟、出包\n   → 修：第一天就接 GitHub Actions\n\n❌ 4. logs 寫進 file\n   → 機器掛了 logs 也沒了\n   → 修：永遠 stdout、外部蒐集\n\n❌ 5. 沒監控、出事才知道\n   → 客戶 email 罵了才發現掛 2 小時\n   → 修：metric + alert + uptime monitor\n```\n\n  \n### 9. 一個典型 startup 的部署棧\n\n```text\n🏗️ source 控制：GitHub\n🔄 CI/CD：     GitHub Actions\n📦 build：     Docker / Vercel build\n☁️ runtime：   Vercel（frontend）+ Railway（API + DB）\n🗄️ DB：        Supabase / Neon\n🔐 secrets：   Vercel env / Doppler\n📊 monitor：   Sentry（errors）+ Vercel Analytics\n📝 logs：      Logtail / BetterStack\n🚨 alerts：    Slack webhook\n```\n\n  \n### 10. 學完這章你會的\n\n```text\n✅ Docker 包你的 app\n✅ GitHub Actions 寫 CI/CD pipeline\n✅ Railway / Fly.io / Render 部署 backend\n✅ Zero-downtime 升級（藍綠 / canary）\n✅ k8s 基礎概念\n✅ 用 Terraform 寫基礎設施\n✅ 故障時看 log / metric 找問題\n```\n\n  \n### 🎯 重點回顧\n\n- **部署 5 階段**：Dev → Build → Artifact → Runtime → 監控\n- **6 種 deploy 方式**——從機房到 Edge、各有適用\n- **環境**：Dev / Staging / Production 至少 3 套\n- **12-Factor App** 是業界血淚教訓\n- **CI / CD 自動化**——push 就 deploy\n- **4 種 runtime**：PaaS / Container / Serverless / VM\n- **監控四要素**：Metrics / Logs / Traces / Alerts\n\n> 💡 **下一課（L3 Railway / Fly.io / Render）**：3 大新世代 PaaS 怎麼選、跟 Vercel 比哪個好。\n\n**☕ 用人話講**\n\n部署總圖——**寫完 code 到使用者真的用到，中間有約 10 個環節**（測試、打包、上線、健康檢查…）。**一句話記住**：像出版一本書——寫完稿（code）到讀者拿到書，中間有印刷、裝訂、鋪貨（部署各環節）；不是「寫完就自動到使用者手上」，這條路要打通。\n",
      "tip": {
        "type": "milestone",
        "text": "Indie 2026：Vercel + Railway + Cloudflare 三巨頭夠用。"
      },
      "id": "22.1",
      "number": "LESSON 22.1",
      "xp": 10,
      "playgrounds": [
        {
          "key": "22.1.auto",
          "language": "bash",
          "title": "從 dev 到 production 的部署步驟",
          "initialCode": "#!/bin/bash\n# 寫完 code 到使用者用得到，中間這些環節\necho \"1. 本機開發   -> 寫 code、跑測試\"\necho \"2. 推上 Git   -> git push\"\necho \"3. CI 自動測  -> 跑測試、檢查品質\"\necho \"4. 建置打包   -> 編譯 / docker build\"\necho \"5. 部署上線   -> 推到伺服器 / 平台\"\necho \"6. 健康檢查   -> 確認服務正常運作\"\necho \"\"\necho \"出問題時能一鍵 rollback 回上一個版本\"",
          "hint": "部署不是只 push，中間有一連串環節要打通。"
        }
      ],
      "exercise": {
        "question": "找一個你身邊的例子、用「部署總圖：從 dev 到 production」的概念解釋它。例如：你常用的 app、新聞看到的事件、生活遇到的問題。",
        "hint": "概念不是用來背、是用來看世界的鏡子。找一個具體場景、套用這節的觀點分析、能套通就是會了。",
        "answer": "三步：(1) 挑一個具體場景（不要太抽象）(2) 列出這節提到的關鍵概念 (3) 用每個概念分析這個場景的某個面向。寫成 300 字內、放進你的學習筆記。"
      },
      "outline": [
        {
          "level": 2,
          "text": "部署選項"
        },
        {
          "level": 3,
          "text": "1. Serverless（Indie 首選）"
        },
        {
          "level": 3,
          "text": "2. PaaS"
        },
        {
          "level": 3,
          "text": "3. IaaS"
        },
        {
          "level": 3,
          "text": "4. K8s"
        },
        {
          "level": 2,
          "text": "部署管道"
        },
        {
          "level": 3,
          "text": "手動"
        },
        {
          "level": 3,
          "text": "CI/CD"
        },
        {
          "level": 2,
          "text": "Static vs SSR vs Container"
        },
        {
          "level": 3,
          "text": "Static"
        },
        {
          "level": 3,
          "text": "SSR（Server-Side Rendering）"
        },
        {
          "level": 3,
          "text": "Container（Docker）"
        },
        {
          "level": 2,
          "text": "Indie 選擇"
        },
        {
          "level": 2,
          "text": "心法"
        }
      ]
    },
    {
      "title": "Docker 入門",
      "oneLineSummary": "把 app 跟所有依賴打包成 image、到處都能跑",
      "analogy": "寫一次、跑遍 macOS / Linux / 雲端。",
      "content": "## 為什麼 Docker\n- 不用「在我電腦跑得起來」\n- 一份 image 跨平台\n- 隔離（不污染 host）\n- 部署簡單\n- 版本控制\n\n## 三個核心\n- **Image**：模板（唯讀）\n- **Container**：跑起來的 instance\n- **Dockerfile**：image 配方\n\n## Hello World\n\n![Docker Desktop 安裝 + 第一次 build / run](/lesson-img/ch22/ch22_docker_desktop.png)\n\n`Dockerfile`：\n```dockerfile\nFROM node:20-alpine\nWORKDIR /app\nCOPY package*.json ./\nRUN npm ci\nCOPY . .\nEXPOSE 3000\nCMD [\"node\", \"server.js\"]\n```\n\n```bash\n# Build\ndocker build -t my-app .\n\n# Run\ndocker run -p 3000:3000 my-app\n\n# List\ndocker ps\ndocker images\n\n# Stop\ndocker stop <container_id>\n```\n\n## 多階段 build（重要）\n```dockerfile\n# Stage 1: Build\nFROM node:20-alpine AS builder\nWORKDIR /app\nCOPY package*.json ./\nRUN npm ci\nCOPY . .\nRUN npm run build\n\n# Stage 2: Production\nFROM node:20-alpine\nWORKDIR /app\nCOPY --from=builder /app/dist ./dist\nCOPY --from=builder /app/node_modules ./node_modules\nCOPY --from=builder /app/package.json ./\nEXPOSE 3000\nCMD [\"node\", \"dist/server.js\"]\n```\n\nImage 小、安全（沒 build 工具）。\n\n## docker-compose（多容器）\n`docker-compose.yml`：\n```yaml\nservices:\n  app:\n    build: .\n    ports: [\"3000:3000\"]\n    environment:\n      DATABASE_URL: postgresql://user:pass@db:5432/app\n    depends_on: [db, redis]\n  \n  db:\n    image: postgres:16\n    environment:\n      POSTGRES_USER: user\n      POSTGRES_PASSWORD: pass\n      POSTGRES_DB: app\n    volumes:\n      - pg_data:/var/lib/postgresql/data\n  \n  redis:\n    image: redis:7-alpine\n    volumes:\n      - redis_data:/data\n\nvolumes:\n  pg_data:\n  redis_data:\n```\n\n```bash\ndocker compose up -d\ndocker compose logs -f app\ndocker compose down\n```\n\n## 環境變數\n```bash\ndocker run -e DATABASE_URL=... -p 3000:3000 my-app\n\n# 或用 .env\ndocker run --env-file .env -p 3000:3000 my-app\n```\n\n## Volume（持久化）\n```bash\n# Bind mount（dev）\ndocker run -v $(pwd):/app my-app\n\n# Named volume（production）\ndocker run -v app_data:/app/data my-app\n```\n\n## .dockerignore\n```\nnode_modules\n.git\n.env\n*.log\n.DS_Store\n```\n\n## Image registry\n- **Docker Hub**：免費 public、付費 private\n- **GitHub Container Registry**：免費 private（個人）\n- **AWS ECR**：AWS 整合\n- **GCP Artifact Registry**\n\n```bash\ndocker tag my-app username/my-app:latest\ndocker push username/my-app:latest\n```\n\n## 常用指令\n```bash\ndocker ps                  # running containers\ndocker ps -a               # 全部（含停止）\ndocker logs <id>           # 看 log\ndocker exec -it <id> sh    # 進入 container\ndocker stats               # 看資源用量\ndocker system prune -a     # 清空\n```\n\n## 體積優化\n- 用 `alpine` 變體（最小）\n- 多階段 build\n- 合併 RUN（減少 layer）\n- .dockerignore\n\n## 心法\n- Dockerfile 是「可重現的環境」\n- 永遠 multi-stage\n- 不要在 image 內存 secrets\n- docker-compose 適合 dev / 小 production\n- K8s 大規模才需要\n\n**☕ 用人話講**\n\nDocker 入門——**把 app 跟它需要的所有依賴打包成一個 image**，讓「在我電腦能跑」變成「到處都能跑」。**一句話記住**：像貨櫃——把貨（app）連同包裝（依賴、環境）一起裝進標準貨櫃（image），不管搬到哪台機器（哪艘船）都長一樣、都能跑，徹底解決「在我電腦明明可以」的問題。\n",
      "tip": {
        "type": "milestone",
        "text": "Docker 是「環境的 Git」。學一次、用一輩子。"
      },
      "id": "22.2",
      "number": "LESSON 22.2",
      "xp": 10,
      "playgrounds": [
        {
          "key": "22.2.auto",
          "language": "bash",
          "title": "試試看",
          "initialCode": "# Build\ndocker build -t my-app .\n\n# Run\ndocker run -p 3000:3000 my-app\n\n# List\ndocker ps\ndocker images\n\n# Stop\ndocker stop <container_id>",
          "hint": "改 code、按執行看結果"
        }
      ],
      "exercise": {
        "question": "用一張紙、把「Docker 入門」的核心概念畫成心智圖。中心是這節的主題、第一圈放 3-5 個關鍵詞（如 Dockerfile、docker-compose.yml、alpine）、第二圈延伸細節。",
        "hint": "關鍵概念可以從 lesson 內出現的這些關鍵字入手：Dockerfile、docker-compose.yml、alpine。畫完不要光放著、試著用自己的話講一次。",
        "answer": "心智圖三步：(1) 中心 = lesson 主題 (2) 第一圈 = 主要分類（通常 3-5 個）(3) 第二圈 = 具體例子或工具。畫完拿給朋友看、能講通 = 真懂。常見錯誤：抄關鍵字當分類、應該用自己理解後的歸納。"
      },
      "outline": [
        {
          "level": 2,
          "text": "為什麼 Docker"
        },
        {
          "level": 2,
          "text": "三個核心"
        },
        {
          "level": 2,
          "text": "Hello World"
        },
        {
          "level": 2,
          "text": "多階段 build（重要）"
        },
        {
          "level": 2,
          "text": "docker-compose（多容器）"
        },
        {
          "level": 2,
          "text": "環境變數"
        },
        {
          "level": 2,
          "text": "Volume（持久化）"
        },
        {
          "level": 2,
          "text": ".dockerignore"
        },
        {
          "level": 2,
          "text": "Image registry"
        },
        {
          "level": 2,
          "text": "常用指令"
        },
        {
          "level": 2,
          "text": "體積優化"
        },
        {
          "level": 2,
          "text": "心法"
        }
      ]
    },
    {
      "title": "Railway / Fly.io / Render",
      "oneLineSummary": "PaaS 三巨頭、Indie 部署 server 首選",
      "analogy": "不寫 Dockerfile 也行、寫了更好。",
      "content": "**Railway / Fly.io / Render = 新世代 PaaS（Platform as a Service、平台即服務）**。**比 Heroku 便宜、比 AWS 簡單、push code 就跑**。各有強項——選對能省 70% 成本 + 90% 設定時間。\n\n> 💡 **這課的價值**：2026 年的 backend 部署不應該還在 SSH 進 EC2 自己裝 nginx。學會這 3 大平台 = 你的 side project / startup 可以 5 分鐘上線。\n\n  \n### 1. PaaS 的演進\n\n```text\n🟢 第一代：Heroku（2007）\n   - PaaS 開山始祖\n   - 簡單到爆\n   - 2022 取消免費方案、貴到不行\n\n🟡 第二代：Vercel / Netlify（2015 ~）\n   - 為前端 / Jamstack 設計\n   - 不適合 long-running backend / DB\n\n🔵 第三代：Railway / Fly.io / Render（2020 ~）\n   - 為「全棧」設計\n   - backend / DB / cron / worker 全包\n   - 比 Heroku 便宜 5 倍\n```\n\n  \n### 2. 三大平台速覽\n\n```text\n┌─────────────┬─────────────────────────────────┐\n│ Railway     │ 最簡單、UI 漂亮、DB 整合超好    │\n│ Fly.io      │ 全球 edge、低延遲、技術控最愛   │\n│ Render      │ 平衡、像新版 Heroku             │\n└─────────────┴─────────────────────────────────┘\n```\n\n  \n### 3. Railway（最簡單）\n\n🌐 **網址**：railway.app\n\n**特色**：\n```text\n✅ 連 GitHub → push 即部署\n✅ 內建 PostgreSQL / MySQL / Redis / MongoDB\n✅ 環境變數 UI 編輯\n✅ 服務間自動 DNS（DATABASE_URL 自動注入）\n✅ Preview environment per PR\n✅ pricing：$5/月起、按用量\n```\n\n**最爽用法**：\n\n🖥️ **在終端機輸入**：\n\n```text\n# 安裝 CLI\nnpm i -g @railway/cli\nrailway login\n\n# 在你的 project\nrailway init\nrailway up    # ← 整個 deploy\n```\n\n💬 **電腦會顯示**：\n\n```text\n✓ Building...\n✓ Deploying...\n✓ https://your-app.up.railway.app\n```\n\n**加 PostgreSQL**：\n- UI：點 `+ New → Database → PostgreSQL`\n- DATABASE_URL 自動注入到你的 app\n- 完成\n\n**何時用**：\n- side project / MVP\n- 不想學 Docker\n- 要 backend + DB 一起\n\n**注意**：\n- 不是 serverless、有 idle cost\n- 流量大時不算便宜\n\n  \n### 4. Fly.io（全球 edge）\n\n🌐 **網址**：fly.io\n\n**特色**：\n```text\n✅ 真正全球部署（30+ 城市）\n✅ 你的 app 跑在 multiple region 同步\n✅ 自動就近 routing（台灣用戶打東京）\n✅ 支援 stateful（持久磁碟）\n✅ 跑 Docker container\n✅ pricing：$5/月免費額度、超出按用量\n```\n\n📄 **寫進程式檔**：`fly.toml`\n\n```text\napp = \"my-app\"\nprimary_region = \"nrt\"   # 東京\n\n[build]\n  dockerfile = \"Dockerfile\"\n\n[http_service]\n  internal_port = 3000\n  force_https = true\n  auto_stop_machines = true     # 沒流量自動關\n  auto_start_machines = true    # 有流量自動開\n  min_machines_running = 0\n\n[[vm]]\n  cpu_kind = \"shared\"\n  cpus = 1\n  memory_mb = 512\n```\n\n🖥️ **在終端機輸入**：\n\n```text\n# 安裝\nbrew install flyctl\n\n# 一次部署\nfly launch         # 自動偵測 + 產生 fly.toml\nfly deploy\n\n# 加 region\nfly regions add sin   # 新加坡\nfly scale count 3 --region sin\n```\n\n**何時用**：\n- 全球用戶（東南亞 + 美國 + 歐洲都有）\n- 對延遲敏感\n- 想跑特殊 binary（不只 Node.js）\n\n  \n### 5. Render（最平衡）\n\n🌐 **網址**：render.com\n\n**特色**：\n```text\n✅ 像新版 Heroku、最像「正常 PaaS」\n✅ 內建 PostgreSQL / Redis\n✅ Web Service / Cron Job / Static Site / Worker 都有\n✅ 自動 HTTPS + 自訂 domain\n✅ Preview environment\n✅ pricing：$7/月起\n```\n\n📄 **寫進程式檔**：`render.yaml`\n\n```text\nservices:\n  - type: web\n    name: my-api\n    env: node\n    buildCommand: npm install && npm run build\n    startCommand: npm start\n    envVars:\n      - key: DATABASE_URL\n        fromDatabase:\n          name: my-db\n          property: connectionString\n\ndatabases:\n  - name: my-db\n    plan: starter\n```\n\n**何時用**：\n- 從 Heroku 搬家\n- 中型 production app\n- 要穩定不要花俏\n\n  \n### 6. 跟 Vercel 比較\n\n```text\n                Vercel       Railway      Fly.io       Render\n────────────────────────────────────────────────────────────────\n強項            前端         全棧         全球 edge    平衡\nServerless      ✅           ❌           ❌           ❌\nContainer       ❌           ✅           ✅           ✅\nDB 託管         ❌（接外部） ✅           ❌           ✅\nCold start      有           無           無           無\nLong task       ❌（10s上限）✅           ✅           ✅\nRegion          全球 CDN     1 region     多 region    3 region\npricing         $20/月       $5/月        $5/月        $7/月\n─────────────────────────────────────────────────────────────\n最佳場景        Next.js      backend+DB   低延遲       傳統 PaaS\n```\n\n  \n### 7. 完整 deploy 範例 — Next.js + PostgreSQL\n\n#### a. Vercel + Supabase（最熱組合）\n\n```text\n1. Vercel deploy Next.js（前端）\n2. Supabase 託管 PostgreSQL\n3. Vercel env：DATABASE_URL = supabase 給的\n4. 完成\n```\n\n#### b. Railway 一鍵全包\n\n```text\n1. Railway → New Project\n2. Deploy from GitHub\n3. + Database → PostgreSQL\n4. 環境變數自動注入\n5. 完成\n```\n\n#### c. Fly.io（要全球）\n\n```text\n1. fly launch\n2. fly postgres create\n3. fly postgres attach\n4. fly deploy\n5. fly regions add ams（阿姆斯特丹）\n```\n\n  \n### 8. 進階：multi-region 配置\n\n**Fly.io 的拿手好戲**：\n\n```text\n# 在多個 region 跑 web service\nfly scale count 3 --region nrt   # 東京 3 台\nfly scale count 2 --region iad   # 維吉尼亞 2 台\nfly scale count 2 --region ams   # 阿姆斯特丹 2 台\n\n# DB 主機 + read replica\nfly postgres create --region nrt    # primary\nfly postgres replica create --region iad\nfly postgres replica create --region ams\n```\n\n**結果**：\n- 台灣用戶 → 東京 server（30ms）\n- 美國用戶 → 維吉尼亞 server（20ms）\n- 歐洲用戶 → 阿姆斯特丹 server（10ms）\n\n  \n### 9. 成本估算（小型 production）\n\n```text\n情境：1 個 backend + 1 個 PostgreSQL + 月 100 萬 request\n\nVercel + Supabase：~$45/月（Pro plans）\nRailway：         ~$15/月（hobby + DB）\nFly.io：          ~$10/月（小規模免費額度大）\nRender：          ~$20/月（Starter + DB）\nAWS（EC2+RDS）：  ~$60/月（要懂 ops）\n```\n\n  \n### 10. 移植性 — 不要被鎖死\n\n```text\n🟢 標準化（容易搬家）：\n   - 用 Docker\n   - 用 PostgreSQL（任何雲都有）\n   - 環境變數讀 config\n   - 12-Factor App\n\n🔴 平台鎖死（搬家痛）：\n   - Vercel 專屬：Edge Functions、ISR\n   - Railway 專屬：很少（基本標準）\n   - Fly.io 專屬：很少\n   - Lambda 專屬：API Gateway integration\n```\n\n  \n### 11. 5 大常見坑\n\n```text\n❌ 1. 把 backend 塞進 Vercel\n   → cold start + 10 秒超時\n   → 修：backend 用 Railway / Fly / Render\n\n❌ 2. Railway free tier 跑 production\n   → 每月用完就停\n   → 修：升 hobby ($5) 起跳\n\n❌ 3. Fly.io 沒設 auto-stop\n   → 沒流量也燒錢\n   → 修：auto_stop_machines = true\n\n❌ 4. 沒設健康檢查\n   → app crash 平台不知道、不重啟\n   → 修：加 /health endpoint + healthcheck 設定\n\n❌ 5. secrets 寫進 code commit\n   → GitHub 一 push 全洩漏\n   → 修：用平台 env 管理、加 .gitignore\n```\n\n  \n### 🎯 重點回顧\n\n- **Railway** 最簡單、適合 MVP / side project\n- **Fly.io** 全球 edge、適合對延遲敏感的全球 app\n- **Render** 最平衡、像新版 Heroku\n- **Vercel** 前端王、backend 不適合\n- **Multi-region** 是 Fly.io 殺手鐧\n- **永遠用 Docker + 環境變數** 保持移植性\n\n> 💡 **下一課（L6 Docker 基礎）**：把你的 app 包成 container、學會 Dockerfile 5 個關鍵 instruction。\n\n**☕ 用人話講**\n\nRailway / Fly.io / Render——**PaaS 三巨頭**，是 indie 部署後端伺服器的首選，連上 GitHub 就自動部署。**一句話記住**：像租一間「附管理的店面」——你只管擺貨（推 code），水電網路、伺服器維運平台都幫你顧，比自己從零蓋房（自架機器）省事太多。\n",
      "tip": {
        "type": "practical",
        "text": "Railway 5 分鐘部署、Fly.io 全球 30 城市。"
      },
      "id": "22.3",
      "number": "LESSON 22.3",
      "xp": 10,
      "playgrounds": [
        {
          "key": "22.3.auto",
          "language": "bash",
          "title": "試試看",
          "initialCode": "brew install flyctl\nfly auth login\nfly launch  # 自動建 fly.toml + Dockerfile\n\nfly deploy\nfly logs\nfly ssh console",
          "hint": "改 code、按執行看結果"
        }
      ],
      "exercise": {
        "question": "打開編輯器、把本節 lesson 內的 code 範例 copy 進去、自己跑一次。然後改 1-2 個參數、觀察結果變化。",
        "hint": "課程內有 5 段 code 範例。先確保能跑得通、再開始改。改的時候一次只改一個變數、才能看出因果。",
        "answer": "三階段：(1) **完整 copy**：先確保環境能跑（裝套件、設環境變數、解錯）(2) **小改觀察**：改字串 / 數字、看輸出 (3) **重寫**：把整段 code 闔起來、靠自己重寫一次、卡住再打開看。重寫一次 = 抄 10 次。"
      },
      "outline": [
        {
          "level": 2,
          "text": "Railway"
        },
        {
          "level": 3,
          "text": "為什麼"
        },
        {
          "level": 3,
          "text": "部署"
        },
        {
          "level": 3,
          "text": "railway.toml"
        },
        {
          "level": 2,
          "text": "Fly.io"
        },
        {
          "level": 3,
          "text": "為什麼"
        },
        {
          "level": 3,
          "text": "部署"
        },
        {
          "level": 3,
          "text": "fly.toml"
        },
        {
          "level": 3,
          "text": "多 region"
        },
        {
          "level": 2,
          "text": "Render"
        },
        {
          "level": 3,
          "text": "為什麼"
        },
        {
          "level": 3,
          "text": "部署"
        },
        {
          "level": 3,
          "text": "render.yaml"
        },
        {
          "level": 2,
          "text": "三巨頭對比"
        },
        {
          "level": 2,
          "text": "Indie 選擇"
        },
        {
          "level": 2,
          "text": "替代"
        },
        {
          "level": 3,
          "text": "Heroku"
        },
        {
          "level": 3,
          "text": "DigitalOcean App Platform"
        },
        {
          "level": 3,
          "text": "AWS App Runner"
        },
        {
          "level": 3,
          "text": "Google Cloud Run"
        },
        {
          "level": 2,
          "text": "心法"
        }
      ]
    },
    {
      "title": "Vercel / Cloudflare Workers",
      "oneLineSummary": "Edge 部署、全球毫秒級",
      "analogy": "前端 + API 邊緣化、cold start 趨近 0。",
      "content": "## Edge Computing\n\n### vs Serverless\n- Serverless：跑在 region（如 us-east-1）\n- Edge：跑在 user 最近的 city（300+ 城市）\n\n### 優點\n- Latency 低（< 50ms）\n- 全球分散\n- 自動 scale\n\n### 限制\n- 不能用 Node API（部分）\n- 不能跑長任務\n- DB connection 要 pool\n\n## Vercel Edge Functions\n```typescript\n// app/api/hello/route.ts\nexport const runtime = \"edge\";\n\nexport async function GET(req: Request) {\n  const country = req.headers.get(\"x-vercel-ip-country\");\n  return Response.json({ hello: country });\n}\n```\n\n只能用 Web standard API（fetch / Response / Crypto）。\n\n## Cloudflare Workers\n```typescript\n// src/index.ts\nexport default {\n  async fetch(request: Request, env: Env) {\n    const url = new URL(request.url);\n    \n    if (url.pathname === \"/api/hello\") {\n      return Response.json({ hello: \"world\" });\n    }\n    \n    return new Response(\"Not found\", { status: 404 });\n  }\n};\n```\n\n部署：\n```bash\nnpm install -g wrangler\nwrangler init my-worker\nwrangler dev    # 本地\nwrangler deploy # 上線\n```\n\n## Cloudflare 生態\n- **Workers**：edge function\n- **R2**：S3 替代、免費 10GB\n- **KV**：edge key-value\n- **D1**：edge SQL\n- **Durable Objects**：stateful\n- **Queues**：訊息佇列\n\n```typescript\n// 全部整合一起\nexport default {\n  async fetch(request, env) {\n    // KV\n    const cached = await env.MY_KV.get(\"key\");\n    \n    // R2\n    const obj = await env.MY_BUCKET.get(\"file.png\");\n    \n    // D1\n    const result = await env.DB.prepare(\"SELECT * FROM users WHERE id = ?\")\n      .bind(userId).first();\n    \n    return Response.json(result);\n  }\n};\n```\n\n## 免費額度（驚人）\n- 100,000 req/天\n- 10ms CPU / req\n- 10MB worker\n- R2：10GB\n- D1：5M reads / day\n\nIndie 可永遠免費。\n\n## Hono（Workers 框架）\n```typescript\nimport { Hono } from \"hono\";\n\nconst app = new Hono();\n\napp.get(\"/\", c => c.json({ hello: \"world\" }));\napp.get(\"/users/:id\", async c => {\n  const id = c.req.param(\"id\");\n  const user = await c.env.DB.prepare(\"SELECT * FROM users WHERE id = ?\")\n    .bind(id).first();\n  return c.json(user);\n});\n\nexport default app;\n```\n\n跑在 Workers / Bun / Node / Deno、跨平台。\n\n## Next.js + Cloudflare\n- Next.js 15 開始原生支援 Edge\n- 用 `@opennextjs/cloudflare` 跑 Next.js 在 Workers\n\n```bash\nnpx create-next-app --use-cloudflare\n```\n\n## Cron Triggers\n```toml\n# wrangler.toml\n[triggers]\ncrons = [\"0 3 * * *\"]\n```\n\n```typescript\nexport default {\n  async scheduled(event, env) {\n    // 每天 3am 跑\n    await runDailyJob();\n  }\n};\n```\n\n## Limits\n\n### Vercel Edge\n- 1MB code\n- 30s timeout\n- 4MB response\n\n### Cloudflare Workers\n- 10MB code（Free 1MB）\n- 30s wall clock\n- 50ms CPU（Free 10ms）\n- 128MB memory\n\n長任務 → Queue / Durable Objects。\n\n## 心法\n- Static + API 邊緣化 = 最快\n- 但 DB connection 要 pool（Hyperdrive）\n- 不適合長任務 / 重計算\n- Cloudflare 免費額度大、Indie 可永遠免費\n\n**☕ 用人話講**\n\nVercel / Cloudflare Workers——**Edge 部署**：把程式放到全球邊緣節點、就近服務、毫秒級回應。**一句話記住**：像連鎖店開遍全球——使用者就近找最近的分店（邊緣節點）拿東西，不用每次都飛到總部（單一伺服器）；全球各地打開都超快。\n",
      "tip": {
        "type": "milestone",
        "text": "Edge = 2026 趨勢。Cloudflare Workers 是 Indie 救星。"
      },
      "id": "22.4",
      "number": "LESSON 22.4",
      "xp": 10,
      "playgrounds": [
        {
          "key": "22.4.auto",
          "language": "bash",
          "title": "試試看",
          "initialCode": "npm install -g wrangler\nwrangler init my-worker\nwrangler dev    # 本地\nwrangler deploy # 上線",
          "hint": "改 code、按執行看結果"
        }
      ],
      "exercise": {
        "question": "打開編輯器、把本節 lesson 內的 code 範例 copy 進去、自己跑一次。然後改 1-2 個參數、觀察結果變化。",
        "hint": "課程內有 8 段 code 範例。先確保能跑得通、再開始改。改的時候一次只改一個變數、才能看出因果。",
        "answer": "三階段：(1) **完整 copy**：先確保環境能跑（裝套件、設環境變數、解錯）(2) **小改觀察**：改字串 / 數字、看輸出 (3) **重寫**：把整段 code 闔起來、靠自己重寫一次、卡住再打開看。重寫一次 = 抄 10 次。"
      },
      "outline": [
        {
          "level": 2,
          "text": "Edge Computing"
        },
        {
          "level": 3,
          "text": "vs Serverless"
        },
        {
          "level": 3,
          "text": "優點"
        },
        {
          "level": 3,
          "text": "限制"
        },
        {
          "level": 2,
          "text": "Vercel Edge Functions"
        },
        {
          "level": 2,
          "text": "Cloudflare Workers"
        },
        {
          "level": 2,
          "text": "Cloudflare 生態"
        },
        {
          "level": 2,
          "text": "免費額度（驚人）"
        },
        {
          "level": 2,
          "text": "Hono（Workers 框架）"
        },
        {
          "level": 2,
          "text": "Next.js + Cloudflare"
        },
        {
          "level": 2,
          "text": "Cron Triggers"
        },
        {
          "level": 2,
          "text": "Limits"
        },
        {
          "level": 3,
          "text": "Vercel Edge"
        },
        {
          "level": 3,
          "text": "Cloudflare Workers"
        },
        {
          "level": 2,
          "text": "心法"
        }
      ]
    },
    {
      "title": "部署 Best Practices",
      "oneLineSummary": "不是把 code 推上去就好、有 SOP",
      "analogy": "減少出事、加快迭代。",
      "content": "## 環境分離\n- Development：本地\n- Staging：preview deploy\n- Production：正式\n\n各自獨立 DB / Secrets。\n\n## CI/CD Pipeline\n```yaml\n# .github/workflows/deploy.yml\nname: Deploy\non:\n  push:\n    branches: [main]\n\njobs:\n  deploy:\n    runs-on: ubuntu-latest\n    steps:\n      - uses: actions/checkout@v4\n      - uses: actions/setup-node@v4\n      - run: npm ci\n      - run: npm run lint\n      - run: npm test\n      - run: npm run build\n      - uses: amondnet/vercel-action@v25\n        with:\n          vercel-token: ${{ secrets.VERCEL_TOKEN }}\n          vercel-args: \"--prod\"\n```\n\n## Health Check\n```typescript\n// /api/health\nexport async function GET() {\n  try {\n    await db.$queryRaw`SELECT 1`;\n    return Response.json({ status: \"ok\" });\n  } catch {\n    return Response.json({ status: \"fail\" }, { status: 503 });\n  }\n}\n```\n\n平台用這個判斷 instance 健康。\n\n## Graceful Shutdown\n```typescript\nprocess.on(\"SIGTERM\", async () => {\n  console.log(\"Shutting down...\");\n  await server.close();\n  await db.disconnect();\n  process.exit(0);\n});\n```\n\n避免 deploy 時切斷 in-progress request。\n\n## Migration 順序\n```\n1. Backward-compatible migration（加新欄、不破壞）\n2. Deploy new code（可同時用舊 / 新 schema）\n3. 等穩定\n4. 下次 deploy 清舊欄位\n```\n\n⚠️ 不要：\n- Deploy 前 drop column\n- 直接改 type\n- 沒 backfill 加 NOT NULL\n\n## Blue-Green Deploy\n- 兩個 environment（Blue + Green）\n- Blue 跑 production\n- Deploy 到 Green\n- 測 Green\n- 切流量 Blue → Green\n- 出事切回\n\nVercel / Cloudflare 自動類似機制。\n\n## Canary\n- 1% 流量到新版\n- 看指標\n- OK → 10% → 50% → 100%\n\n## Rollback Plan\n- 部署前知道怎麼 rollback\n- Vercel UI 一鍵\n- 寫 rollback script\n\n## 監控部署\n- Sentry 看 error rate\n- Datadog 看 latency\n- Better Stack 看 uptime\n\n異常 → 立刻 rollback。\n\n## 環境變數管理\n\n### Doppler\n```bash\ndoppler setup\ndoppler run -- npm start\n```\n集中管理、跨平台同步。\n\n### 1Password CLI\n```bash\nop run -- npm start\n```\n\n### Vercel / Railway env\n平台內建。\n\n## Secrets Rotation\n定期換：\n- API key：每 90 天\n- DB password：每 180 天\n- JWT secret：每年\n\n## 不要在 production\n- console.log（用 logger）\n- 開 debug mode\n- assert（會 crash）\n- 寫 file（無 persistent storage）\n\n## 部署時機\n- ❌ 週五下午\n- ❌ 大假期前\n- ❌ 流量高峰\n- ✅ 週二早上\n- ✅ 流量低峰\n\n## Post-deploy Checklist\n- [ ] 監控 30 分鐘\n- [ ] 看 Sentry\n- [ ] 客服 channel\n- [ ] 24 小時後 review\n\n## 心法\n- staging 永遠先測\n- 監控不要瞎飛\n- Rollback 比修補快\n- 週五不部署\n- 一致流程、不要憑感覺\n\n**☕ 用人話講**\n\n部署 Best Practices——**不是把 code 推上去就好**，要有 SOP：環境變數、健康檢查、準備好回滾。**一句話記住**：像飛機起飛前的檢查表——一項項確認過了才放行，而不是憑感覺直接衝；有 SOP，上線出包的機率就大幅下降、出事也救得回。\n",
      "tip": {
        "type": "milestone",
        "text": "部署流程化 = 不靠運氣、靠 system。"
      },
      "id": "22.5",
      "number": "LESSON 22.5",
      "xp": 10,
      "playgrounds": [
        {
          "key": "22.5.auto",
          "language": "yaml",
          "title": "試試看",
          "initialCode": "# .github/workflows/deploy.yml\nname: Deploy\non:\n  push:\n    branches: [main]\n\njobs:\n  deploy:\n    runs-on: ubuntu-latest\n    steps:\n      - uses: actions/checkout@v4\n      - uses: actions/setup-node@v4\n      - run: npm ci\n      - run: npm run lint\n      - run: npm test\n      - run: npm run build\n      - uses: amondnet/vercel-action@v25\n        with:\n          vercel-token: ${{ secrets.VERCEL_TOKEN }}\n          vercel-args: \"--prod\"",
          "hint": "改 code、按執行看結果"
        }
      ],
      "exercise": {
        "question": "打開編輯器、把本節 lesson 內的 code 範例 copy 進去、自己跑一次。然後改 1-2 個參數、觀察結果變化。",
        "hint": "課程內有 6 段 code 範例。先確保能跑得通、再開始改。改的時候一次只改一個變數、才能看出因果。",
        "answer": "三階段：(1) **完整 copy**：先確保環境能跑（裝套件、設環境變數、解錯）(2) **小改觀察**：改字串 / 數字、看輸出 (3) **重寫**：把整段 code 闔起來、靠自己重寫一次、卡住再打開看。重寫一次 = 抄 10 次。"
      },
      "outline": [
        {
          "level": 2,
          "text": "環境分離"
        },
        {
          "level": 2,
          "text": "CI/CD Pipeline"
        },
        {
          "level": 2,
          "text": "Health Check"
        },
        {
          "level": 2,
          "text": "Graceful Shutdown"
        },
        {
          "level": 2,
          "text": "Migration 順序"
        },
        {
          "level": 2,
          "text": "Blue-Green Deploy"
        },
        {
          "level": 2,
          "text": "Canary"
        },
        {
          "level": 2,
          "text": "Rollback Plan"
        },
        {
          "level": 2,
          "text": "監控部署"
        },
        {
          "level": 2,
          "text": "環境變數管理"
        },
        {
          "level": 3,
          "text": "Doppler"
        },
        {
          "level": 3,
          "text": "1Password CLI"
        },
        {
          "level": 3,
          "text": "Vercel / Railway env"
        },
        {
          "level": 2,
          "text": "Secrets Rotation"
        },
        {
          "level": 2,
          "text": "不要在 production"
        },
        {
          "level": 2,
          "text": "部署時機"
        },
        {
          "level": 2,
          "text": "Post-deploy Checklist"
        },
        {
          "level": 2,
          "text": "心法"
        }
      ]
    },
    {
      "title": "Docker 基礎",
      "oneLineSummary": "把 App 包成 container、到處跑",
      "analogy": "不再「我電腦能跑啊」。",
      "content": "**Docker = 把「整個 OS + 程式 + 設定」打包成一個檔案**——叫做 image。在任何電腦跑這個 image 結果都一樣。**解決「我電腦跑得起來、你電腦跑不起來」這個千古難題**。\n\n> 💡 **這課的價值**：2026 年所有部署 90% 都用 container。學會 Docker = 你可以把 app deploy 到任何雲、不被綁死。\n\n  \n### 1. 核心三個概念\n\n```text\n🧊 Image（映像）\n   - 「打包好的程式 + OS」\n   - 一個唯讀檔\n   - 例：nginx:1.27、postgres:16\n\n📦 Container（容器）\n   - image 跑起來的「實例」\n   - 像 class vs object 的關係\n   - 一個 image 可以跑很多 container\n\n📋 Dockerfile（建構檔）\n   - 一份文字食譜\n   - 告訴 docker「怎麼做出這個 image」\n```\n\n  \n### 2. 跟 VM 比較\n\n```text\n🖥️ Virtual Machine（虛擬機）\n   - 整個 OS（GB 等級）\n   - 開機要分鐘\n   - 隔離強\n\n📦 Container\n   - 只裝差異層（MB 等級）\n   - 啟動秒級\n   - 共享 host kernel\n   - 隔離夠用\n\n→ Container 是「輕量版 VM」\n```\n\n  \n### 3. 第一個 Dockerfile\n\n📄 **寫進程式檔**：`Dockerfile`\n\n```text\n# 從哪個 image 開始（base）\nFROM node:20-alpine\n\n# 設工作目錄\nWORKDIR /app\n\n# 複製檔案進 image\nCOPY package*.json ./\nRUN npm ci\n\nCOPY . .\n\n# 開放 port\nEXPOSE 3000\n\n# 啟動指令\nCMD [\"node\", \"server.js\"]\n```\n\n🖥️ **在終端機輸入**：\n\n```text\n# Build image\ndocker build -t my-app:1.0 .\n\n# 跑 container\ndocker run -p 3000:3000 my-app:1.0\n```\n\n💬 **電腦會顯示**：\n\n```text\nServer listening on http://localhost:3000\n```\n\n  \n### 4. Dockerfile 12 個 instruction\n\n```text\nFROM         base image（必須）\nWORKDIR      設工作目錄\nCOPY         複製本機檔案到 image\nADD          像 COPY 但能解壓 / 抓 URL（少用）\nRUN          build 階段執行指令（裝套件）\nENV          設環境變數\nARG          build-time 參數\nEXPOSE       宣告 port（純文件）\nVOLUME       宣告掛載點\nUSER         切換 user（安全）\nCMD          預設啟動指令（可被覆蓋）\nENTRYPOINT   進入點（不被覆蓋）\nHEALTHCHECK  健康檢查\n```\n\n**CMD vs ENTRYPOINT**：\n\n```text\nCMD [\"node\", \"server.js\"]\n  → docker run image            跑 node server.js\n  → docker run image bash       跑 bash（覆蓋）\n\nENTRYPOINT [\"node\"]\nCMD [\"server.js\"]\n  → docker run image            跑 node server.js\n  → docker run image other.js   跑 node other.js（CMD 被覆蓋）\n```\n\n  \n### 5. Layer（層）— 為什麼順序重要\n\n每個指令產生一層、cache 起來。**沒變的 layer 不重 build**。\n\n❌ **錯誤順序**：\n\n```text\nCOPY . .\nRUN npm install\n```\n\n→ 改一個 source code、整個 npm install 重跑（慢）。\n\n✅ **正確順序**：\n\n```text\nCOPY package*.json ./\nRUN npm ci\nCOPY . .\n```\n\n→ 只改 source 不改 package.json → npm ci 用 cache（快 10 倍）。\n\n**口訣**：**「越穩定的放前面、越常變的放後面」**。\n\n  \n### 6. Multi-stage Build（多階段建置）\n\n**問題**：build 需要 1.2GB 的工具（compiler、devDeps）、跑只需要 100MB。\n\n**解法**：分兩階段、最後只留 runtime。\n\n📄 **寫進程式檔**：`Dockerfile`\n\n```text\n# Stage 1: builder\nFROM node:20 AS builder\nWORKDIR /app\nCOPY package*.json ./\nRUN npm ci\nCOPY . .\nRUN npm run build\n\n# Stage 2: runtime（只留必要的）\nFROM node:20-alpine\nWORKDIR /app\nCOPY --from=builder /app/dist ./dist\nCOPY --from=builder /app/node_modules ./node_modules\nCOPY package.json .\nCMD [\"node\", \"dist/server.js\"]\n```\n\n**結果**：image 從 1.2GB → 180MB。\n\n  \n### 7. .dockerignore（必寫）\n\n📄 **寫進程式檔**：`.dockerignore`\n\n```text\nnode_modules\n.git\n.env\n.env.local\n*.log\ncoverage/\n.next/\ndist/\nREADME.md\n.vscode/\n```\n\n**作用**：build context 上傳不會把這些丟進去（更快、更安全）。\n\n  \n### 8. docker-compose — 多 service 編排\n\n📄 **寫進程式檔**：`docker-compose.yml`\n\n```text\nservices:\n  web:\n    build: .\n    ports:\n      - \"3000:3000\"\n    environment:\n      DATABASE_URL: postgres://user:pass@db:5432/mydb\n      REDIS_URL: redis://cache:6379\n    depends_on:\n      - db\n      - cache\n\n  db:\n    image: postgres:16-alpine\n    environment:\n      POSTGRES_USER: user\n      POSTGRES_PASSWORD: pass\n      POSTGRES_DB: mydb\n    volumes:\n      - pg_data:/var/lib/postgresql/data\n    ports:\n      - \"5432:5432\"\n\n  cache:\n    image: redis:7-alpine\n    ports:\n      - \"6379:6379\"\n\nvolumes:\n  pg_data:\n```\n\n🖥️ **在終端機輸入**：\n\n```text\ndocker compose up         # 一次跑全部\ndocker compose up -d      # 背景跑\ndocker compose logs -f web   # 看 log\ndocker compose down       # 全停\n```\n\n  \n### 9. 常用 base image 推薦\n\n```text\n🐳 Node.js\n   node:20-alpine        最小（80MB）\n   node:20-slim          中等\n   node:20               完整（1GB+）\n\n🐍 Python\n   python:3.12-slim      推薦\n   python:3.12-alpine    更小但 wheel 可能不相容\n\n🐹 Go\n   golang:1.22-alpine    build\n   scratch / distroless   runtime（< 10MB）\n\n🦀 Rust\n   rust:alpine           build\n   debian:bookworm-slim  runtime\n\n🌐 全能\n   ubuntu:24.04          穩、大\n   debian:bookworm-slim  穩、小\n   alpine:3.20           最小但 musl 可能踩雷\n```\n\n  \n### 10. 安全最佳實踐\n\n```text\n✅ 不以 root 跑\n   USER node\n   \n✅ 用具體版本（不要用 latest）\n   FROM node:20.11.0-alpine  ✅\n   FROM node:latest          ❌（會偷偷升）\n\n✅ 不要 COPY secrets 進去\n   用 BuildKit secrets、或 runtime env\n\n✅ 掃漏洞\n   docker scout cves my-app:1.0\n   trivy image my-app:1.0\n\n✅ multi-stage 減少 attack surface\n\n✅ HEALTHCHECK 加上\n   HEALTHCHECK --interval=30s CMD curl -f http://localhost:3000/health || exit 1\n```\n\n  \n### 11. 常用指令清單\n\n🖥️ **在終端機輸入**：\n\n```text\n# Image\ndocker build -t name:tag .       建構\ndocker images                    列出\ndocker rmi image_id              刪除\ndocker pull nginx                拉取\ndocker push my/image:tag         推送\n\n# Container\ndocker run -p 3000:3000 -d name  跑\ndocker ps                        看在跑的\ndocker ps -a                     全部（含停的）\ndocker logs container_id         看 log\ndocker logs -f container_id      跟著看\ndocker exec -it container bash   進去\ndocker stop container_id         停\ndocker rm container_id           刪\ndocker restart container_id      重啟\n\n# 清理\ndocker system prune              清沒用的\ndocker system prune -a --volumes 全清（小心）\n\n# Compose\ndocker compose up -d             跑\ndocker compose ps                看狀態\ndocker compose logs -f service   看 log\ndocker compose down              停\n```\n\n  \n### 12. 5 大常見坑\n\n```text\n❌ 1. 把 node_modules COPY 進去\n   → image 巨大、不同 OS 模組爆\n   → 修：.dockerignore + RUN npm ci\n\n❌ 2. 用 latest tag\n   → 哪天 base image 升 → 你的 app 突然壞\n   → 修：用具體版本（node:20.11.0-alpine）\n\n❌ 3. ENV 寫死 secrets\n   → image push 出去 = 洩漏\n   → 修：runtime 才注入\n\n❌ 4. 沒 multi-stage\n   → image 1.2GB、pull 半天\n   → 修：build / runtime 分階段\n\n❌ 5. 沒 .dockerignore\n   → 把 .git / node_modules 都打包進去\n   → 修：第一天就寫 .dockerignore\n```\n\n  \n### 🎯 重點回顧\n\n- **Image** 是模板、**Container** 是實例、**Dockerfile** 是食譜\n- **Layer 順序**：穩定的放前面、常變的放後面（cache 友善）\n- **Multi-stage build** 把 image 縮小 5 ~ 10 倍\n- **.dockerignore** 第一天就寫\n- **docker-compose** 編排多 service（web + db + cache）\n- **不要用 latest**、不要 root 跑、不要 COPY secrets\n\n> 💡 **下一課（L7 CI/CD GitHub Actions）**：學會寫 workflow、push code 自動 build / test / deploy。\n\n**☕ 用人話講**\n\nDocker 基礎——把 App 包成 container、到處跑：用 Dockerfile 定義 → build 成 image → run 成 container。**一句話記住**：食譜（Dockerfile）→ 照食譜做出半成品（image）→ 上桌那一盤（container）；一套流程，就能在任何機器複製出一模一樣的環境。\n",
      "tip": {
        "type": "practical",
        "text": "Multi-stage + alpine = 標準做法。"
      },
      "exercise": {
        "question": "打開編輯器、把本節 lesson 內的 code 範例 copy 進去、自己跑一次。然後改 1-2 個參數、觀察結果變化。",
        "hint": "課程內有 5 段 code 範例。先確保能跑得通、再開始改。改的時候一次只改一個變數、才能看出因果。",
        "answer": "三階段：(1) **完整 copy**：先確保環境能跑（裝套件、設環境變數、解錯）(2) **小改觀察**：改字串 / 數字、看輸出 (3) **重寫**：把整段 code 闔起來、靠自己重寫一次、卡住再打開看。重寫一次 = 抄 10 次。"
      },
      "id": "22.6",
      "number": "LESSON 22.6",
      "xp": 10,
      "playgrounds": [
        {
          "key": "22.6.auto",
          "language": "bash",
          "title": "試試看",
          "initialCode": "docker build -t myapp:1.0 .\ndocker run -p 3000:3000 myapp:1.0",
          "hint": "改 code、按執行看結果"
        }
      ],
      "outline": [
        {
          "level": 2,
          "text": "是什麼"
        },
        {
          "level": 3,
          "text": "vs 虛擬機"
        },
        {
          "level": 2,
          "text": "Dockerfile 範例"
        },
        {
          "level": 2,
          "text": "Build + Run"
        },
        {
          "level": 2,
          "text": "docker-compose"
        },
        {
          "level": 2,
          "text": "Multi-stage Build（縮 image 大小）"
        },
        {
          "level": 2,
          "text": "心法"
        }
      ]
    },
    {
      "title": "CI/CD：GitHub Actions",
      "oneLineSummary": "不再手動 deploy、push 就上線",
      "analogy": "一次設定、永遠省時。",
      "content": "**GitHub Actions = GitHub 內建的 CI/CD 系統**——push code 自動跑 test、build、deploy。**寫一個 YAML 檔、推上去就行**。**業界最普及、免費額度爆炸大**。\n\n> 💡 **這課的價值**：手動 deploy 是上世紀的事。學會 GitHub Actions = 你的 PR 自動測試、合 main 自動上線、不用記任何指令。\n\n  \n### 1. 核心概念\n\n```text\n📋 Workflow（工作流）\n   一個 YAML 檔、在 .github/workflows/ 下\n   例：ci.yml、deploy.yml\n\n⚡ Event（事件）\n   什麼時候觸發 workflow\n   例：push、pull_request、schedule\n\n🧱 Job（任務）\n   workflow 內的「平行單位」\n   - 各自有自己的 runner\n   - 互不影響（除非 needs）\n\n🪜 Step（步驟）\n   job 內的「依序動作」\n   - 跑 shell command\n   - 或用別人的 Action\n\n🔌 Action（行動）\n   別人寫好的 reusable 步驟\n   - actions/checkout\n   - actions/setup-node\n   - 用 - uses: name@version 呼叫\n```\n\n  \n### 2. 第一個 workflow\n\n📄 **寫進程式檔**：`.github/workflows/ci.yml`\n\n```text\nname: CI\n\non:\n  push:\n    branches: [main]\n  pull_request:\n    branches: [main]\n\njobs:\n  test:\n    runs-on: ubuntu-latest\n\n    steps:\n      - name: Checkout code\n        uses: actions/checkout@v4\n\n      - name: Setup Node.js\n        uses: actions/setup-node@v4\n        with:\n          node-version: '20'\n          cache: 'npm'\n\n      - name: Install dependencies\n        run: npm ci\n\n      - name: Lint\n        run: npm run lint\n\n      - name: Typecheck\n        run: npm run typecheck\n\n      - name: Test\n        run: npm test\n\n      - name: Build\n        run: npm run build\n```\n\n**push 上去後**：GitHub 自動跑、UI 看綠勾 / 紅叉。\n\n  \n### 3. Workflow 結構詳解\n\n```text\nname: ...                # workflow 名稱（UI 顯示）\n\non:                      # 觸發事件\n  push:                  # push 時\n    branches: [main]\n  pull_request:          # PR 時\n  schedule:              # 排程\n    - cron: '0 3 * * *'  # 每天 3am\n  workflow_dispatch:     # 手動觸發按鈕\n  release:               # 發 release 時\n\njobs:\n  job_id:                # 你取的 id\n    runs-on: ubuntu-latest   # 用什麼機器\n    needs: [other_job]   # 等其他 job 跑完\n    if: github.ref == 'refs/heads/main'   # 條件\n    timeout-minutes: 10\n    \n    strategy:            # 矩陣（同 job 跑多版本）\n      matrix:\n        node: [18, 20, 22]\n        os: [ubuntu-latest, windows-latest]\n    \n    steps:\n      - uses: ...        # 用 action\n      - run: ...         # 跑 shell\n      - name: ...        # 顯示名稱\n```\n\n  \n### 4. Secrets — 密鑰管理\n\n**設定路徑**：repo → Settings → Secrets and variables → Actions\n\n```text\nDATABASE_URL = postgres://...\nDISCORD_WEBHOOK = https://discord.com/...\nRAILWAY_TOKEN = xxxxx\nVERCEL_TOKEN = yyyyy\n```\n\n**在 workflow 用**：\n\n```text\n- name: Deploy\n  env:\n    DATABASE_URL: ${{ secrets.DATABASE_URL }}\n  run: npm run deploy\n```\n\n**重要**：\n- Secrets 在 log 自動 mask（顯示為 `***`）\n- PR from fork 拿不到 secrets（安全）\n\n  \n### 5. 完整 example：test + deploy\n\n📄 **寫進程式檔**：`.github/workflows/deploy.yml`\n\n```text\nname: Deploy\n\non:\n  push:\n    branches: [main]\n\njobs:\n  test:\n    runs-on: ubuntu-latest\n    steps:\n      - uses: actions/checkout@v4\n      - uses: actions/setup-node@v4\n        with:\n          node-version: '20'\n          cache: 'npm'\n      - run: npm ci\n      - run: npm test\n\n  deploy-staging:\n    needs: test\n    runs-on: ubuntu-latest\n    environment: staging\n    steps:\n      - uses: actions/checkout@v4\n      - name: Deploy to Railway\n        uses: bervProject/railway-deploy@v3\n        with:\n          railway_token: ${{ secrets.RAILWAY_TOKEN }}\n          service: my-app-staging\n\n  e2e:\n    needs: deploy-staging\n    runs-on: ubuntu-latest\n    steps:\n      - uses: actions/checkout@v4\n      - run: npm ci\n      - run: npx playwright test\n        env:\n          BASE_URL: https://staging.my-app.com\n\n  deploy-prod:\n    needs: e2e\n    runs-on: ubuntu-latest\n    environment:\n      name: production\n      url: https://my-app.com\n    steps:\n      - uses: actions/checkout@v4\n      - name: Deploy to Railway\n        uses: bervProject/railway-deploy@v3\n        with:\n          railway_token: ${{ secrets.RAILWAY_TOKEN }}\n          service: my-app-prod\n\n      - name: Notify Slack\n        uses: slackapi/slack-github-action@v1\n        with:\n          webhook: ${{ secrets.SLACK_WEBHOOK }}\n          payload: '{\"text\":\"deployed v${{ github.sha }} to prod\"}'\n```\n\n**流程**：\n```text\npush main\n  ↓\ntest ─→ deploy-staging ─→ e2e ─→ deploy-prod ─→ Slack\n```\n\n  \n### 6. Matrix — 同一 job 跑多版本\n\n```text\njobs:\n  test:\n    runs-on: ${{ matrix.os }}\n    strategy:\n      matrix:\n        os: [ubuntu-latest, macos-latest, windows-latest]\n        node: [18, 20, 22]\n        # 3 × 3 = 9 個 job 平行跑\n    steps:\n      - uses: actions/setup-node@v4\n        with:\n          node-version: ${{ matrix.node }}\n      - run: npm test\n```\n\n  \n### 7. Action Marketplace（市集）\n\n🌐 **github.com/marketplace?type=actions**\n\n**最常用的**：\n\n```text\n🔧 基礎\n   actions/checkout@v4            把 code 拿下來\n   actions/setup-node@v4          裝 Node.js\n   actions/setup-python@v5        裝 Python\n   actions/cache@v4               cache 任何檔案\n\n📦 Build / Deploy\n   docker/build-push-action@v5    build + push Docker\n   vercel/action@v3               deploy 到 Vercel\n   appleboy/ssh-action@v1         SSH 到 server\n\n🧪 Test\n   codecov/codecov-action@v4      上傳 coverage\n   peter-evans/create-pull-request 自動開 PR\n\n🔔 通知\n   slackapi/slack-github-action   發 Slack\n   8398a7/action-slack            另一個 Slack\n```\n\n  \n### 8. Build & Push Docker image\n\n📄 **寫進程式檔**：`.github/workflows/docker.yml`\n\n```text\nname: Docker\n\non:\n  push:\n    branches: [main]\n    tags: ['v*']\n\njobs:\n  build:\n    runs-on: ubuntu-latest\n    permissions:\n      contents: read\n      packages: write\n    steps:\n      - uses: actions/checkout@v4\n\n      - name: Login to GHCR\n        uses: docker/login-action@v3\n        with:\n          registry: ghcr.io\n          username: ${{ github.actor }}\n          password: ${{ secrets.GITHUB_TOKEN }}\n\n      - name: Setup Buildx\n        uses: docker/setup-buildx-action@v3\n\n      - name: Build & push\n        uses: docker/build-push-action@v5\n        with:\n          context: .\n          push: true\n          tags: |\n            ghcr.io/${{ github.repository }}:latest\n            ghcr.io/${{ github.repository }}:${{ github.sha }}\n          cache-from: type=gha\n          cache-to: type=gha,mode=max\n```\n\n  \n### 9. 進階：Reusable Workflow\n\n**避免重複**：把常用 workflow 抽出來。\n\n📄 **寫進程式檔**：`.github/workflows/_test.yml`\n\n```text\nname: Reusable Test\n\non:\n  workflow_call:\n    inputs:\n      node-version:\n        type: string\n        default: '20'\n\njobs:\n  test:\n    runs-on: ubuntu-latest\n    steps:\n      - uses: actions/checkout@v4\n      - uses: actions/setup-node@v4\n        with:\n          node-version: ${{ inputs.node-version }}\n      - run: npm ci\n      - run: npm test\n```\n\n**用它**：\n\n```text\njobs:\n  call-test:\n    uses: ./.github/workflows/_test.yml\n    with:\n      node-version: '22'\n```\n\n  \n### 10. Environment（環境）\n\n```text\njobs:\n  deploy-prod:\n    environment:\n      name: production\n      url: https://my-app.com   # PR 顯示\n```\n\n**設定**：repo → Settings → Environments → New\n\n- 加 **required reviewer**（合人才能 deploy）\n- 加 **wait timer**（合後 5 分鐘才跑）\n- 設環境特定 secrets\n\n  \n### 11. 免費額度\n\n```text\n🟢 Free (個人 + open source)\n   公開 repo：無限\n   私人 repo：2000 分鐘/月\n\n🟡 Pro ($4/月)\n   3000 分鐘/月\n\n🔵 Team ($4/user/月)\n   3000 分鐘/月共享\n   並發更多\n\n→ 大多數 startup 免費就夠\n```\n\n  \n### 12. 5 大常見坑\n\n```text\n❌ 1. secrets 寫進 yaml\n   → push 上去 = 洩漏\n   → 修：永遠用 ${{ secrets.X }}\n\n❌ 2. 沒設 timeout-minutes\n   → 卡住的 job 跑 6 小時、燒額度\n   → 修：每個 job 加 timeout-minutes: 30\n\n❌ 3. 沒 cache\n   → 每次 npm ci 重抓、慢 5 倍\n   → 修：actions/setup-node 加 cache: 'npm'\n\n❌ 4. PR from fork 拿不到 secrets 嚇到\n   → 修：用 pull_request_target（小心安全）\n       或讓 deploy 只跑在 push main\n\n❌ 5. 一個 workflow 100 行混雜\n   → 修：拆 reusable workflow\n```\n\n  \n### 🎯 重點回顧\n\n- **GitHub Actions = .github/workflows/*.yml**\n- **核心**：Event → Job → Step → Action\n- **Marketplace** 有上萬 action 直接用\n- **Secrets** 在 repo settings 設、用 `${{ secrets.X }}`\n- **Matrix** 同 job 跑多版本\n- **Reusable workflow** 避免重複\n- **Environment** 加 reviewer 防 deploy 出包\n\n> 💡 **下一課（L8 Zero-downtime Deploy）**：deploy 怎麼做到「使用者完全感覺不到在升級」——藍綠 / canary / rolling。\n\n**☕ 用人話講**\n\nCI/CD（GitHub Actions）——**不再手動部署**，push 之後自動測試、build、上線。**一句話記住**：像自動生產線——你只管 push，後面「測試 → 打包 → 上線」全自動跑完；省去每次手動操作，也少掉「忘了跑測試就上線」的人為失誤。\n",
      "tip": {
        "type": "milestone",
        "text": "CI/CD setup 一次、永遠省時。"
      },
      "exercise": {
        "question": "打開編輯器、把本節 lesson 內的 code 範例 copy 進去、自己跑一次。然後改 1-2 個參數、觀察結果變化。",
        "hint": "課程內有 5 段 code 範例。先確保能跑得通、再開始改。改的時候一次只改一個變數、才能看出因果。",
        "answer": "三階段：(1) **完整 copy**：先確保環境能跑（裝套件、設環境變數、解錯）(2) **小改觀察**：改字串 / 數字、看輸出 (3) **重寫**：把整段 code 闔起來、靠自己重寫一次、卡住再打開看。重寫一次 = 抄 10 次。"
      },
      "id": "22.7",
      "number": "LESSON 22.7",
      "xp": 10,
      "playgrounds": [
        {
          "key": "22.7.auto",
          "language": "yaml",
          "title": "試試看",
          "initialCode": "name: Deploy\n\non:\n  push:\n    branches: [main]\n\njobs:\n  test:\n    runs-on: ubuntu-latest\n    steps:\n      - uses: actions/checkout@v4\n      - uses: actions/setup-node@v4\n        with: { node-version: 20 }\n      - run: npm ci\n      - run: npm test\n      - run: npm run lint\n\n  deploy:\n    needs: test\n    runs-on: ubuntu-latest\n    if: github.ref == 'refs/heads/main'\n    steps:\n      - uses: actions/checkout@v4\n      - name: Deploy to Vercel\n        run: |\n          npm install -g vercel\n          vercel --prod --token=${{ secrets.VERCEL_TOKEN }}",
          "hint": "改 code、按執行看結果"
        }
      ],
      "outline": [
        {
          "level": 2,
          "text": "基本 workflow"
        },
        {
          "level": 2,
          "text": "Secrets"
        },
        {
          "level": 2,
          "text": "多環境"
        },
        {
          "level": 2,
          "text": "Matrix（多版本測試）"
        },
        {
          "level": 2,
          "text": "Cache 加速"
        },
        {
          "level": 2,
          "text": "Build Docker + Push"
        },
        {
          "level": 2,
          "text": "心法"
        }
      ]
    },
    {
      "title": "Zero-downtime Deploy",
      "oneLineSummary": "上線時不能掛、要無縫切換",
      "analogy": "5 秒 down 都會被罵。",
      "content": "**Zero-downtime Deploy（零停機部署）= deploy 新版本時、使用者感覺不到任何中斷**。**4 大策略**：藍綠（blue-green）、金絲雀（canary）、滾動（rolling）、feature flag。**沒做 = 每次 deploy 客戶都看到 502**。\n\n> 💡 **這課的價值**：上線到一定流量後一定要懂。學會 = 你能凌晨 3 點 deploy、客戶毫無感覺。Netflix / Google / Vercel 都這樣做。\n\n  \n### 1. 傳統 deploy 為什麼會 down\n\n```text\nnaive deploy：\n1. 停舊版（5 秒～ 1 分鐘）\n2. 換 code\n3. 啟動新版（10 秒 ～ 1 分鐘）\n\n→ 中間這段使用者看到：\n   - 502 Bad Gateway\n   - \"Service Unavailable\"\n   - 連線斷掉\n\n→ 流量大時：每次 deploy 影響上萬人\n```\n\n  \n### 2. 4 大策略\n\n```text\n策略           原理                     風險   成本   速度\n────────────────────────────────────────────────────────\nRolling        逐台替換                 中     低     中\nBlue-Green     雙環境切換                低     高     快\nCanary         先給 1% 試               低     中     慢\nFeature Flag   code 上線 + 開關控制      最低   低     可分段\n```\n\n  \n### 3. Rolling Update（滾動更新）\n\n**最常見、k8s 預設**：1 台 1 台慢慢替換。\n\n```text\nBefore：v1 v1 v1 v1 v1     (5 台都是舊)\nStep 1：v2 v1 v1 v1 v1     (殺第 1 台、起新版)\nStep 2：v2 v2 v1 v1 v1\nStep 3：v2 v2 v2 v1 v1\nStep 4：v2 v2 v2 v2 v1\nAfter： v2 v2 v2 v2 v2     (全新版)\n```\n\n**優點**：✅ 不用雙倍機器、簡單\n**缺點**：⚠️ deploy 過程中有「v1 + v2 共存」——要相容\n        ⚠️ 出包要 rolling back、慢\n\n📄 **寫進程式檔**：`k8s-deployment.yaml`\n\n```text\nspec:\n  replicas: 5\n  strategy:\n    type: RollingUpdate\n    rollingUpdate:\n      maxUnavailable: 1   # 一次最多 1 台不可用\n      maxSurge: 1         # 一次最多多開 1 台\n```\n\n  \n### 4. Blue-Green Deployment（藍綠部署）\n\n**兩個完全一樣的環境、切換流量**。\n\n```text\nBefore：\n   Blue  (v1)  ← 所有流量\n   Green (none)\n\nDeploy：\n   Blue  (v1)  ← 流量\n   Green (v2)  ← 部署完成、跑 smoke test\n\nSwitch（DNS / Load Balancer 切換）：\n   Blue  (v1)  ← 0 流量、留著當 rollback\n   Green (v2)  ← 所有流量\n\n完成（24 小時後）：\n   Blue → 升級成 v2 待命\n   Green (v2)\n```\n\n**優點**：\n- ✅ 切換瞬間完成\n- ✅ Rollback 也是瞬間（切回 Blue）\n- ✅ 不用 v1 + v2 相容\n\n**缺點**：\n- ⚠️ 要雙倍機器（貴）\n- ⚠️ DB schema migration 處理麻煩\n\n**工具**：\n- AWS：CodeDeploy 內建\n- k8s：用 Service selector 切\n- Fly.io：fly deploy --strategy bluegreen\n\n  \n### 5. Canary Deployment（金絲雀部署）\n\n**先給 1% 流量試、沒事再放大**——名字來自礦工帶金絲雀下礦（牠先死你才知道有毒）。\n\n```text\nPhase 1：1% 流量 → v2\n        99% 流量 → v1\n        \n        觀察 10 分鐘\n        - error rate？\n        - latency？\n        - business metrics（轉換率）？\n\nPhase 2（沒問題）：10% → v2、90% → v1\nPhase 3：25% → v2、75% → v1\nPhase 4：50% → v2、50% → v1\nPhase 5：100% → v2\n\nPhase X（有問題）：立刻拉回 0%\n```\n\n**優點**：\n- ✅ 風險最低\n- ✅ 真實流量驗證\n- ✅ 自動 rollback（metric 不對就停）\n\n**缺點**：\n- ⚠️ deploy 時間長（小時～天）\n- ⚠️ 要好的 metric / observability\n- ⚠️ v1 + v2 要相容\n\n**工具**：\n- k8s + Argo Rollouts / Flagger\n- Istio / Linkerd（service mesh）\n- AWS App Mesh\n\n📄 **Argo Rollouts 範例**：\n\n```text\nspec:\n  strategy:\n    canary:\n      steps:\n        - setWeight: 1     # 1% 流量到新版\n        - pause: { duration: 10m }\n        - setWeight: 10\n        - pause: { duration: 10m }\n        - setWeight: 25\n        - pause: { duration: 10m }\n        - setWeight: 50\n        - pause: { duration: 10m }\n        - setWeight: 100\n      analysis:           # 自動看 metric\n        templates:\n          - templateName: error-rate\n        args:\n          - name: service-name\n            value: my-app\n```\n\n  \n### 6. Feature Flag（功能旗標）\n\n**code 上線、但功能用「旗標」控制**——分離 deploy 跟 release。\n\n```text\n傳統：\n   code change ── deploy ── 上線\n\nFeature Flag：\n   code change ── deploy（all users 都 deploy）\n                       ↓\n                  flag = off → 沒人看到新功能\n                       ↓\n                  flag = 1% → 1% 看到\n                       ↓\n                  flag = 100% → 全開\n                       ↓\n                  flag = off → 出問題立刻關\n```\n\n📄 **寫進程式檔**：`feature.ts`\n\n```text\nimport { useFlag } from '@vercel/flags/next';\n\nfunction CheckoutPage() {\n  const newPayment = useFlag('new-payment-flow');\n\n  return newPayment\n    ? <NewPaymentUI />\n    : <OldPaymentUI />;\n}\n```\n\n**工具**：\n- **LaunchDarkly**（業界龍頭）\n- **Unleash**（開源）\n- **PostHog**（含 analytics）\n- **Vercel Flags**\n- **GrowthBook**\n\n**好處**：\n- ✅ deploy 跟 release 解耦\n- ✅ A/B test 同一條 pipeline\n- ✅ 立刻 rollback（關 flag、不用 redeploy）\n- ✅ 漸進式發布\n\n  \n### 7. DB Migration — 零停機的最大挑戰\n\n**問題**：v1 跟 v2 對 schema 要求不一樣。\n\n**Expand → Migrate → Contract**（L19.10 講過）：\n\n```text\nPhase 1：Expand（擴展）\n   - 加新欄位 / 表\n   - v1 不用、v2 用\n   - 兩版本都能跑\n\nPhase 2：Migrate（遷移）\n   - 把 v1 流量切到 v2\n   - 回填舊資料\n\nPhase 3：Contract（收縮）\n   - 確認沒問題後\n   - 拿掉舊欄位 / 表\n```\n\n**例子：把 `name` 拆成 `firstName` / `lastName`**：\n\n```text\nv1 deploy：只用 name\n↓\nDB migration：加 firstName / lastName 欄位（NULL 允許）\n↓\nv2 deploy：v2 寫 firstName / lastName + 維持寫 name\n↓\nbackfill：UPDATE 舊資料、name → firstName + lastName\n↓\nv3 deploy：v3 只用 firstName / lastName\n↓\nDB migration：DROP name 欄位\n```\n\n  \n### 8. Health Check + Graceful Shutdown\n\n**Health Check（健康檢查）**：\n\n📄 **寫進程式檔**：`server.ts`\n\n```text\napp.get('/health', (req, res) => res.json({ ok: true }));\n\napp.get('/ready', async (req, res) => {\n  // 檢查 DB / cache 都正常才回 200\n  try {\n    await db.query('SELECT 1');\n    await redis.ping();\n    res.json({ ready: true });\n  } catch {\n    res.status(503).json({ ready: false });\n  }\n});\n```\n\n**load balancer / k8s**：定期 ping、不健康就停送流量。\n\n**Graceful Shutdown（優雅關閉）**：\n\n```text\nprocess.on('SIGTERM', async () => {\n  console.log('Received SIGTERM, shutting down...');\n\n  // 1. 停接新 request\n  server.close();\n\n  // 2. 等現有 request 結束（最多 30 秒）\n  await new Promise(r => setTimeout(r, 30000));\n\n  // 3. 關 DB / redis 連線\n  await db.end();\n  await redis.quit();\n\n  process.exit(0);\n});\n```\n\n**對 k8s**：`terminationGracePeriodSeconds: 30`\n\n  \n### 9. Rollback — 出包怎麼救\n\n```text\n策略         Rollback 時間   方法\n─────────────────────────────────────\nRolling      5 ~ 30 分鐘     redeploy 舊版（慢）\nBlue-Green   瞬間            切回 Blue\nCanary       立刻            自動偵測停 promotion\nFeature Flag 瞬間            關 flag（不用 redeploy）\n```\n\n**rollback 演習**：每月做一次！不演習真出事手忙腳亂。\n\n  \n### 10. 5 大常見坑\n\n```text\n❌ 1. 沒 health check 直接 deploy\n   → app 還沒 ready 流量就打進來、5xx\n   → 修：永遠加 /health + /ready\n\n❌ 2. SIGTERM 不處理\n   → 進行中的 request 被斬斷\n   → 修：listen SIGTERM、graceful shutdown\n\n❌ 3. DB migration 跟 code deploy 同一步\n   → schema 改了、舊 code 還在跑、爆\n   → 修：Expand → Migrate → Contract\n\n❌ 4. Canary 沒設自動 rollback\n   → 半夜出包、沒人盯著\n   → 修：error rate > 1% 自動拉回\n\n❌ 5. 從沒演習過 rollback\n   → 真出事手忙腳亂\n   → 修：每月做一次 rollback drill\n```\n\n  \n### 🎯 重點回顧\n\n- **4 大策略**：Rolling / Blue-Green / Canary / Feature Flag\n- **Rolling** 簡單便宜、**Blue-Green** 快但貴、**Canary** 風險最低、**Feature Flag** 最彈性\n- **Health Check + Graceful Shutdown** 是基本盤\n- **DB migration 用 Expand → Migrate → Contract** 三段式\n- **Rollback 必須演習**——沒練過 = 真出事抓瞎\n- **Feature Flag** 把 deploy 跟 release 解耦、業界趨勢\n\n> 💡 **下一課（L9 Kubernetes 入門）**：學會 k8s 5 大核心物件、何時該用、何時不該用（學習曲線警告）。\n\n**☕ 用人話講**\n\nZero-downtime Deploy（零停機部署）——**上線時服務不能掛**，要無縫切換（舊版先頂著、新版起來了再切過去）。**一句話記住**：像營業中換招牌——不關店（停機）、邊營業邊換，等新招牌掛穩了才拆舊的，客人完全無感地完成升級。\n",
      "tip": {
        "type": "milestone",
        "text": "Vercel / Zeabur 自動 zero-downtime、Indie 別自己刻。"
      },
      "exercise": {
        "question": "打開編輯器、把本節 lesson 內的 code 範例 copy 進去、自己跑一次。然後改 1-2 個參數、觀察結果變化。",
        "hint": "課程內有 3 段 code 範例。先確保能跑得通、再開始改。改的時候一次只改一個變數、才能看出因果。",
        "answer": "三階段：(1) **完整 copy**：先確保環境能跑（裝套件、設環境變數、解錯）(2) **小改觀察**：改字串 / 數字、看輸出 (3) **重寫**：把整段 code 闔起來、靠自己重寫一次、卡住再打開看。重寫一次 = 抄 10 次。"
      },
      "id": "22.8",
      "number": "LESSON 22.8",
      "xp": 10,
      "playgrounds": [
        {
          "key": "22.8.auto",
          "language": "typescript",
          "title": "試試看",
          "initialCode": "app.get(\"/healthz\", (req, res) => {\n  // 檢查 DB / cache / 外部 service\n  const dbOk = await db.$queryRaw`SELECT 1`;\n  if (!dbOk) return res.status(503).end();\n  res.json({ status: \"ok\" });\n});",
          "hint": "改 code、按執行看結果"
        }
      ],
      "outline": [
        {
          "level": 2,
          "text": "策略"
        },
        {
          "level": 3,
          "text": "1. Rolling Update"
        },
        {
          "level": 3,
          "text": "2. Blue-Green"
        },
        {
          "level": 3,
          "text": "3. Canary"
        },
        {
          "level": 2,
          "text": "Health Check"
        },
        {
          "level": 2,
          "text": "Graceful Shutdown"
        },
        {
          "level": 2,
          "text": "Database Migration"
        },
        {
          "level": 3,
          "text": "規則"
        },
        {
          "level": 2,
          "text": "心法"
        }
      ]
    },
    {
      "title": "Kubernetes 入門",
      "oneLineSummary": "Container orchestration 業界標準",
      "analogy": "小公司用 Vercel 就好、大公司用 K8s。",
      "content": "**Kubernetes（k8s）= Google 開源的「container 大規模管家」**——管 100 台機器上的 1000 個 container、自動調度、自動恢復、自動 scaling。**業界標準、學習曲線最陡**。\n\n> 💡 **這課的價值**：先給警告——99% 的 startup 不需要 k8s、用了反而拖垮 team。但知道它存在、何時該用、概念怎麼運作很重要。\n\n  \n### 1. 警告：你可能不需要 k8s\n\n```text\n❌ 不要用 k8s 如果：\n   - team < 5 人\n   - 沒專職 DevOps\n   - 月流量 < 100 萬\n   - 沒做微服務\n   \n   → 用 Railway / Fly.io / Render 就好\n\n✅ 適合 k8s 如果：\n   - 流量 / 服務數量大（10+ 微服務）\n   - 跨雲、跨 region\n   - 有專職 SRE team\n   - 法規要求自建\n```\n\n**口號**：**「k8s 是 Google 的問題、不是你的問題」**。\n\n  \n### 2. k8s 解什麼問題\n\n```text\n情境：100 個 container 在 50 台機器\n- 哪台機器 down 了、上面的 container 要遷\n- 流量大了、自動加 container\n- 升級不能 down\n- network / storage / secrets 統一管理\n\n裸 Docker：自己刻一個 6 個月 + 永遠在救火\nk8s：寫 yaml 描述「我要什麼」、它幫你達成\n```\n\n**核心理念**：**Declarative（宣告式）**——你說「我要 5 個 web 容器」、k8s 自動維持 5 個。掛 1 個自動補 1 個。\n\n  \n### 3. 五大核心物件\n\n```text\n🧊 Pod（豆莢）\n   - k8s 最小單位\n   - 1 個 Pod = 1+ 個 container 共享網路 + 儲存\n   - 通常一個 Pod 跑一個 app\n   - Pod 是 ephemeral（死了不會回來）\n\n📦 Deployment（部署）\n   - 管 Pod 的「desired state」\n   - 「我要 5 個 nginx」\n   - Pod 掛了自動補\n   - 升級用 rolling update\n\n🌐 Service（服務）\n   - 給 Pod 一個穩定的網址\n   - Pod IP 會變、Service 不會\n   - load balance 流量到多個 Pod\n\n🚪 Ingress（入口）\n   - 把外部流量路由到 Service\n   - 處理 HTTPS、domain routing\n   - 像 nginx / load balancer\n\n🔐 ConfigMap / Secret（設定 / 密鑰）\n   - 環境變數、設定檔\n   - Secret 加密儲存（base64 + 加密）\n```\n\n  \n### 4. 第一個 k8s yaml\n\n📄 **寫進程式檔**：`deployment.yaml`\n\n```text\napiVersion: apps/v1\nkind: Deployment\nmetadata:\n  name: my-app\nspec:\n  replicas: 3              # 我要 3 個\n  selector:\n    matchLabels:\n      app: my-app\n  template:\n    metadata:\n      labels:\n        app: my-app\n    spec:\n      containers:\n        - name: web\n          image: ghcr.io/me/my-app:1.2.3\n          ports:\n            - containerPort: 3000\n          env:\n            - name: DATABASE_URL\n              valueFrom:\n                secretKeyRef:\n                  name: my-secrets\n                  key: db-url\n          resources:\n            requests:\n              memory: \"128Mi\"\n              cpu: \"100m\"\n            limits:\n              memory: \"256Mi\"\n              cpu: \"500m\"\n          livenessProbe:\n            httpGet:\n              path: /health\n              port: 3000\n            periodSeconds: 30\n          readinessProbe:\n            httpGet:\n              path: /ready\n              port: 3000\n            periodSeconds: 5\n---\napiVersion: v1\nkind: Service\nmetadata:\n  name: my-app-svc\nspec:\n  selector:\n    app: my-app\n  ports:\n    - port: 80\n      targetPort: 3000\n  type: ClusterIP\n---\napiVersion: networking.k8s.io/v1\nkind: Ingress\nmetadata:\n  name: my-app-ing\n  annotations:\n    cert-manager.io/cluster-issuer: letsencrypt\nspec:\n  tls:\n    - hosts: [my-app.com]\n      secretName: my-app-tls\n  rules:\n    - host: my-app.com\n      http:\n        paths:\n          - path: /\n            pathType: Prefix\n            backend:\n              service:\n                name: my-app-svc\n                port:\n                  number: 80\n```\n\n🖥️ **在終端機輸入**：\n\n```text\nkubectl apply -f deployment.yaml\n```\n\n💬 **電腦會顯示**：\n\n```text\ndeployment.apps/my-app created\nservice/my-app-svc created\ningress.networking.k8s.io/my-app-ing created\n```\n\n  \n### 5. 常用 kubectl 指令\n\n🖥️ **在終端機輸入**：\n\n```text\n# 看 cluster 狀態\nkubectl get nodes\nkubectl get pods\nkubectl get deploy\nkubectl get svc\nkubectl get ingress\n\n# 看細節\nkubectl describe pod my-app-xxx\nkubectl logs my-app-xxx\nkubectl logs -f my-app-xxx        跟著看\nkubectl logs --previous my-app-xxx  上次 crash 的 log\n\n# 進去 container\nkubectl exec -it my-app-xxx -- bash\n\n# 改 replica\nkubectl scale deployment my-app --replicas=10\n\n# 看歷史\nkubectl rollout history deployment my-app\nkubectl rollout undo deployment my-app   ← rollback\n\n# 刪\nkubectl delete pod my-app-xxx\nkubectl delete -f deployment.yaml\n```\n\n  \n### 6. Auto-scaling — HPA\n\n📄 **寫進程式檔**：`hpa.yaml`\n\n```text\napiVersion: autoscaling/v2\nkind: HorizontalPodAutoscaler\nmetadata:\n  name: my-app-hpa\nspec:\n  scaleTargetRef:\n    apiVersion: apps/v1\n    kind: Deployment\n    name: my-app\n  minReplicas: 2\n  maxReplicas: 20\n  metrics:\n    - type: Resource\n      resource:\n        name: cpu\n        target:\n          type: Utilization\n          averageUtilization: 70\n```\n\n**作用**：CPU > 70% 自動加 Pod、降下來自動減。\n\n  \n### 7. Namespace（命名空間）\n\n```text\n不同環境 / team 隔離：\n- default\n- staging\n- production\n- team-a\n- monitoring\n\nkubectl get pods -n staging\nkubectl apply -f xxx.yaml -n production\n```\n\n  \n### 8. 生態系\n\n```text\n☁️ Managed k8s（不用自己裝）\n   - AWS EKS\n   - Google GKE\n   - Azure AKS\n   - DigitalOcean DOKS\n   - Linode LKE\n\n🛠️ 套件管理\n   - Helm（k8s 的 npm）\n   - Kustomize（覆蓋 yaml）\n\n📊 監控\n   - Prometheus + Grafana\n   - Datadog / New Relic\n\n🔐 secrets 管理\n   - Sealed Secrets\n   - External Secrets Operator\n   - HashiCorp Vault\n\n🚦 流量管理\n   - Istio / Linkerd（service mesh）\n   - Cilium\n\n🤖 GitOps\n   - ArgoCD\n   - Flux\n\n📦 CI/CD on k8s\n   - Tekton\n   - Jenkins X\n   - Argo Workflows\n```\n\n  \n### 9. 真實成本\n\n```text\n☁️ Managed k8s 月費：\n   - control plane：$70 ~ $100（GKE / EKS）\n   - 3 個 node（4core/16GB）：$300 ~ $500\n   - load balancer：$20\n   - 總計：~$500/月（最小可用）\n\n👥 人力成本：\n   - 至少要 1 個 SRE / DevOps\n   - 學習曲線：3 ~ 6 個月才上手\n\n🎯 ROI 怎麼算？\n   - 服務 < 5 個：不划算\n   - 月流量 < 1000 萬：不划算\n   - 月營收 < $10000：不划算\n```\n\n  \n### 10. 學習路徑\n\n```text\nStep 1：本機練習\n   - Kind / Minikube / Docker Desktop k8s\n   - 不要碰 production\n\nStep 2：跑 official tutorial\n   - kubernetes.io/docs/tutorials/\n\nStep 3：考 CKAD（認證）\n   - Certified Kubernetes Application Developer\n\nStep 4：managed k8s 跑 toy project\n\nStep 5：才碰真 production\n\n→ 全程 6 ~ 12 個月\n```\n\n  \n### 11. 5 大常見坑\n\n```text\n❌ 1. startup 小團隊就上 k8s\n   → 全 team 在學 yaml、業務沒推進\n   → 修：先用 Railway / Fly.io、流量到了再說\n\n❌ 2. 沒設 resource limits\n   → 一個 pod 吃光記憶體、整台 node 倒\n   → 修：每個 container 設 requests + limits\n\n❌ 3. 沒 liveness / readiness probe\n   → crash pod 還在 routing、500 滿天飛\n   → 修：永遠加 /health + /ready\n\n❌ 4. secrets 直接 commit\n   → base64 不是加密！\n   → 修：用 Sealed Secrets / External Secrets\n\n❌ 5. 自己裝 k8s（不用 managed）\n   → control plane 維護地獄\n   → 修：用 EKS / GKE / AKS\n```\n\n  \n### 🎯 重點回顧\n\n- **k8s = container 編排系統**——管 1000+ container 自動調度\n- **5 大物件**：Pod / Deployment / Service / Ingress / ConfigMap+Secret\n- **宣告式**——yaml 寫「我要什麼」、k8s 自動維持\n- **HPA** 自動 scaling、根據 CPU / metric\n- **99% startup 不需要 k8s**——先用 Railway / Fly / Render\n- **若一定要用**：用 managed（EKS / GKE）、別自己裝\n\n> 💡 **下一課（L10 IaC）**：用 Terraform 寫程式管理基礎設施、雲端資源「代碼化」。\n\n**☕ 用人話講**\n\nKubernetes 入門——**Container Orchestration（容器調度）的業界標準**：自動管理大量容器的擴展、修復。**一句話記住**：像貨櫃碼頭的調度系統——自動安排幾百個貨櫃（容器）放哪、壞了自動換新、流量大了自動加；規模大到要管很多容器時才需要它。\n",
      "tip": {
        "type": "warning",
        "text": "K8s 不是 「越早用越專業」、是「真的需要才用」。"
      },
      "exercise": {
        "question": "找一個你身邊的例子、用「Kubernetes 入門」的概念解釋它。例如：你常用的 app、新聞看到的事件、生活遇到的問題。",
        "hint": "概念不是用來背、是用來看世界的鏡子。找一個具體場景、套用這節的觀點分析、能套通就是會了。",
        "answer": "三步：(1) 挑一個具體場景（不要太抽象）(2) 列出這節提到的關鍵概念 (3) 用每個概念分析這個場景的某個面向。寫成 300 字內、放進你的學習筆記。"
      },
      "id": "22.9",
      "number": "LESSON 22.9",
      "xp": 10,
      "playgrounds": [
        {
          "key": "22.9.auto",
          "language": "yaml",
          "title": "試試看",
          "initialCode": "apiVersion: v1\nkind: Pod\nmetadata:\n  name: my-app\nspec:\n  containers:\n  - name: app\n    image: myapp:1.0\n    ports:\n    - containerPort: 3000",
          "hint": "改 code、按執行看結果"
        }
      ],
      "outline": [
        {
          "level": 2,
          "text": "何時用 K8s"
        },
        {
          "level": 3,
          "text": "適合"
        },
        {
          "level": 3,
          "text": "不適合（Indie）"
        },
        {
          "level": 2,
          "text": "核心概念"
        },
        {
          "level": 3,
          "text": "Pod"
        },
        {
          "level": 3,
          "text": "Deployment"
        },
        {
          "level": 3,
          "text": "Service"
        },
        {
          "level": 3,
          "text": "Ingress"
        },
        {
          "level": 2,
          "text": "託管 K8s"
        },
        {
          "level": 2,
          "text": "替代方案（Indie）"
        },
        {
          "level": 2,
          "text": "心法"
        }
      ]
    },
    {
      "title": "Infrastructure as Code (IaC)",
      "oneLineSummary": "基礎建設用 code 管、不用滑鼠點",
      "analogy": "Terraform / Pulumi 神器。",
      "content": "**IaC（Infrastructure as Code、基礎設施即代碼）= 用程式碼描述「我要什麼伺服器 / DB / 網路」、跑一下自動建好**。**告別「手動在 AWS console 點來點去」**——所有資源像 git 一樣 review / version。\n\n> 💡 **這課的價值**：手動點 cloud console 是 2015 年的事。學會 IaC = 環境可重現、PR review 基礎設施變更、災難時 5 分鐘重建整套。\n\n  \n### 1. 沒 IaC 的痛點\n\n```text\n❌ 手動建：\n   - 開 EC2 → 點 30 次按鈕\n   - 設 VPC → 又 50 次\n   - 接 RDS → 再 30 次\n   - 半年後同事問「這個 security group 為什麼開」→ 沒人記得\n\n❌ 沒法 review：\n   - 改一個 setting 沒人知道\n   - 改錯沒法 rollback\n\n❌ 災難不可恢復：\n   - 整個 region 倒了\n   - 要在另一個 region 重建 → 一週\n\n✅ IaC：\n   - 寫 terraform 檔\n   - PR review\n   - terraform apply 自動建好\n   - git 歷史就是基礎設施歷史\n   - 換 region 改一個變數 → 30 分鐘重建\n```\n\n  \n### 2. 5 大工具\n\n```text\n🔷 Terraform（HashiCorp、業界 #1）\n   - HCL 語法（HashiCorp Configuration Language）\n   - 多 cloud（AWS / GCP / Azure / Cloudflare ...）\n   - 2023 改 BSL license（社群分叉 OpenTofu）\n\n🍴 OpenTofu（社群分叉）\n   - Terraform 1.5 的 fork\n   - 100% 開源（MPL）\n   - 跟 Terraform 99% 相容\n\n🟪 Pulumi\n   - 用 TS / Python / Go 寫\n   - 適合工程師（不愛 HCL 的）\n\n🔶 AWS CloudFormation\n   - 只支援 AWS\n   - YAML / JSON\n   - AWS 內服務深度整合\n\n☁️ AWS CDK（Cloud Development Kit）\n   - 寫 TS / Python、生成 CloudFormation\n   - 最舒服的 AWS-only\n```\n\n**業界選擇**：\n- 跨雲 / 大廠 → Terraform / OpenTofu\n- AWS 重度 → CDK\n- 喜歡寫程式 → Pulumi\n\n  \n### 3. Terraform 核心概念\n\n```text\n📋 Provider（提供者）\n   要管哪個 cloud\n   例：aws / google / azurerm / cloudflare\n\n📦 Resource（資源）\n   實際的東西\n   例：aws_instance、aws_s3_bucket\n\n📊 State（狀態）\n   Terraform 記錄「目前實際長什麼樣」\n   存在 .tfstate 檔（要存遠端 S3 + lock）\n\n🔄 Plan & Apply\n   plan：看 diff（要建什麼、改什麼、刪什麼）\n   apply：實際執行\n```\n\n  \n### 4. 第一個 Terraform 檔\n\n📄 **寫進程式檔**：`main.tf`\n\n```text\nterraform {\n  required_version = \">= 1.6\"\n  required_providers {\n    aws = {\n      source  = \"hashicorp/aws\"\n      version = \"~> 5.0\"\n    }\n  }\n\n  # State 存遠端\n  backend \"s3\" {\n    bucket         = \"my-tf-state\"\n    key            = \"prod/terraform.tfstate\"\n    region         = \"ap-northeast-1\"\n    dynamodb_table = \"tf-lock\"\n    encrypt        = true\n  }\n}\n\nprovider \"aws\" {\n  region = var.region\n}\n\nvariable \"region\" {\n  type    = string\n  default = \"ap-northeast-1\"\n}\n\nvariable \"env\" {\n  type    = string\n  default = \"production\"\n}\n\n# VPC\nresource \"aws_vpc\" \"main\" {\n  cidr_block = \"10.0.0.0/16\"\n\n  tags = {\n    Name = \"${var.env}-vpc\"\n    Env  = var.env\n  }\n}\n\n# RDS\nresource \"aws_db_instance\" \"main\" {\n  identifier        = \"${var.env}-db\"\n  engine            = \"postgres\"\n  engine_version    = \"16.2\"\n  instance_class    = \"db.t3.medium\"\n  allocated_storage = 50\n  storage_encrypted = true\n\n  db_name  = \"myapp\"\n  username = \"postgres\"\n  password = var.db_password   # 從 var 帶\n\n  backup_retention_period = 7\n  multi_az                = true   # HA\n\n  tags = {\n    Env = var.env\n  }\n}\n\nvariable \"db_password\" {\n  type      = string\n  sensitive = true\n}\n\n# Output 給其他模組 / 人用\noutput \"db_endpoint\" {\n  value = aws_db_instance.main.endpoint\n}\n```\n\n🖥️ **在終端機輸入**：\n\n```text\n# 第一次\nterraform init           裝 providers\n\n# 看計畫\nterraform plan -var=\"db_password=...\"\n\n# 套用\nterraform apply -var=\"db_password=...\"\n\n# 看當前狀態\nterraform show\n\n# 刪一切\nterraform destroy\n```\n\n💬 **電腦會顯示（plan）**：\n\n```text\nTerraform will perform the following actions:\n\n  # aws_vpc.main will be created\n  + resource \"aws_vpc\" \"main\" {\n      + cidr_block = \"10.0.0.0/16\"\n      ...\n    }\n\n  # aws_db_instance.main will be created\n  + resource \"aws_db_instance\" \"main\" {\n      ...\n    }\n\nPlan: 2 to add, 0 to change, 0 to destroy.\n```\n\n  \n### 5. Module — 重用基礎設施\n\n📄 **寫進程式檔**：`modules/web/main.tf`\n\n```text\nvariable \"name\" {}\nvariable \"image\" {}\nvariable \"replicas\" {\n  default = 2\n}\n\nresource \"aws_ecs_service\" \"web\" {\n  name            = var.name\n  task_definition = aws_ecs_task_definition.web.arn\n  desired_count   = var.replicas\n  # ...\n}\n\noutput \"url\" {\n  value = aws_lb.web.dns_name\n}\n```\n\n**使用模組**：\n\n```text\nmodule \"api\" {\n  source   = \"./modules/web\"\n  name     = \"api\"\n  image    = \"ghcr.io/me/api:v1\"\n  replicas = 5\n}\n\nmodule \"worker\" {\n  source   = \"./modules/web\"\n  name     = \"worker\"\n  image    = \"ghcr.io/me/worker:v1\"\n  replicas = 2\n}\n```\n\n**Public module registry**：registry.terraform.io ——找 AWS / GCP 常用 pattern 直接拿。\n\n  \n### 6. Workspace — 多環境\n\n```text\nterraform workspace new dev\nterraform workspace new staging\nterraform workspace new production\n\nterraform workspace select dev\nterraform apply       # 只改 dev 環境\n\n# 在 code 內\nlocals {\n  is_prod = terraform.workspace == \"production\"\n  \n  instance_type = local.is_prod ? \"t3.large\" : \"t3.micro\"\n}\n```\n\n  \n### 7. Pulumi 範例（TS 寫）\n\n📄 **寫進程式檔**：`index.ts`\n\n```text\nimport * as aws from \"@pulumi/aws\";\n\nconst vpc = new aws.ec2.Vpc(\"main\", {\n  cidrBlock: \"10.0.0.0/16\",\n  tags: { Env: \"production\" },\n});\n\nconst db = new aws.rds.Instance(\"main\", {\n  engine: \"postgres\",\n  engineVersion: \"16.2\",\n  instanceClass: \"db.t3.medium\",\n  allocatedStorage: 50,\n  username: \"postgres\",\n  password: process.env.DB_PASSWORD,\n});\n\nexport const dbEndpoint = db.endpoint;\n```\n\n```text\npulumi up\n```\n\n**好處**：完整程式語言（迴圈 / 條件 / npm 套件）。\n\n  \n### 8. State 管理 — 最重要\n\n```text\n⚠️ State 是 IaC 的核心\n   - 記錄當前實際狀態\n   - 不能丟、不能多人同時改\n\n✅ 必做：\n   1. 存遠端（S3 + DynamoDB lock / Terraform Cloud）\n   2. 加密\n   3. 加 lock（防併發寫）\n   4. backup state\n\n❌ 不可：\n   - state 存本機（一個人改 = 衝突）\n   - 手動改 state（搞壞超痛）\n   - 多人同時 apply（無 lock 會壞）\n```\n\n  \n### 9. GitOps 工作流\n\n```text\n1. 工程師改 main.tf\n2. 開 PR → CI 跑 terraform plan\n3. plan 結果貼到 PR comment（diff 可 review）\n4. team review\n5. merge 後 CI 自動 terraform apply\n6. Slack 通知\n```\n\n**工具**：\n- **Atlantis**（最熱）\n- **Terraform Cloud / HCP**\n- **Spacelift**\n- **env0**\n\n  \n### 10. IaC 適用範圍\n\n```text\n✅ 適合 IaC：\n   - VPC / subnet / security group\n   - RDS / S3 / ECS\n   - Load balancer / Route 53\n   - IAM role / policy\n   - k8s cluster\n\n⚠️ 不適合 IaC（用其他工具）：\n   - app 部署（用 k8s yaml / Helm）\n   - DB schema migration（用 Prisma / Flyway）\n   - 真實資料（用備份還原）\n   - secrets 內容（用 Vault / Secret Manager）\n```\n\n  \n### 11. 5 大常見坑\n\n```text\n❌ 1. state 存本機\n   → 同事一改、衝突地獄\n   → 修：第一天就放 S3 + lock\n\n❌ 2. 把 secrets 寫死在 .tf\n   → git push = 洩漏\n   → 修：用 var + sensitive = true、或 Vault\n\n❌ 3. 沒 review 直接 apply\n   → 改錯把 production DB 刪了\n   → 修：永遠先 plan、永遠 PR review\n\n❌ 4. 手動改 console、不更新 .tf\n   → 下次 apply 把你的手動改回去\n   → 修：所有變更走 Terraform、或 import 進來\n\n❌ 5. 不寫 module、複製貼上\n   → dev / staging / prod 三份相似 code\n   → 修：抽 module、用 workspace\n```\n\n  \n### 🎯 重點回顧\n\n- **IaC = 寫程式碼描述基礎設施**——可 review、可 version、可重建\n- **5 大工具**：Terraform / OpenTofu / Pulumi / CloudFormation / CDK\n- **核心**：Provider → Resource → State → Plan & Apply\n- **State 必須存遠端 + lock**——不能本機\n- **Module** 重用、**Workspace** 多環境\n- **GitOps**：PR → plan diff → review → apply 自動化\n- **secrets 不要寫進 .tf**——用 Vault / Secret Manager\n\n> 💡 **下一章**：學完整個部署 + DB + API 三章——你已經能設計一個能撐住 100 萬人的後端架構了。\n\n**☕ 用人話講**\n\nInfrastructure as Code（IaC）——**基礎建設用 code 來管**，不用滑鼠在控制台點來點去，而是用程式碼描述、可版控、可複製。**一句話記住**：像用設計圖蓋房子——不是到現場憑感覺砌磚（手動點介面），而是照圖（code）蓋；要再蓋一棟一模一樣的，直接複製那張圖就行。\n",
      "tip": {
        "type": "milestone",
        "text": "IaC = 基礎建設「可重現」、災難復原從幾天變幾小時。"
      },
      "exercise": {
        "question": "打開編輯器、把本節 lesson 內的 code 範例 copy 進去、自己跑一次。然後改 1-2 個參數、觀察結果變化。",
        "hint": "課程內有 9 段 code 範例。先確保能跑得通、再開始改。改的時候一次只改一個變數、才能看出因果。",
        "answer": "三階段：(1) **完整 copy**：先確保環境能跑（裝套件、設環境變數、解錯）(2) **小改觀察**：改字串 / 數字、看輸出 (3) **重寫**：把整段 code 闔起來、靠自己重寫一次、卡住再打開看。重寫一次 = 抄 10 次。"
      },
      "id": "22.10",
      "number": "LESSON 22.10",
      "xp": 10,
      "playgrounds": [
        {
          "key": "22.10.auto",
          "language": "hcl",
          "title": "試試看",
          "initialCode": "provider \"aws\" {\n  region = \"ap-northeast-1\"\n}\n\nresource \"aws_instance\" \"web\" {\n  ami           = \"ami-xxxxxx\"\n  instance_type = \"t3.small\"\n  \n  tags = {\n    Name = \"WebServer\"\n  }\n}\n\nresource \"aws_s3_bucket\" \"uploads\" {\n  bucket = \"myapp-uploads\"\n  acl    = \"private\"\n}",
          "hint": "改 code、按執行看結果"
        }
      ],
      "outline": [
        {
          "level": 2,
          "text": "為什麼 IaC"
        },
        {
          "level": 3,
          "text": "痛點"
        },
        {
          "level": 3,
          "text": "解"
        },
        {
          "level": 2,
          "text": "主流工具"
        },
        {
          "level": 3,
          "text": "Terraform（最熱）"
        },
        {
          "level": 3,
          "text": "Pulumi"
        },
        {
          "level": 3,
          "text": "CloudFormation"
        },
        {
          "level": 3,
          "text": "Ansible"
        },
        {
          "level": 2,
          "text": "工作流"
        },
        {
          "level": 3,
          "text": "1. 寫 code"
        },
        {
          "level": 3,
          "text": "2. Init"
        },
        {
          "level": 3,
          "text": "3. Plan（預覽變動）"
        },
        {
          "level": 3,
          "text": "4. Apply"
        },
        {
          "level": 3,
          "text": "5. Destroy（拆掉所有資源）"
        },
        {
          "level": 2,
          "text": "State 管理"
        },
        {
          "level": 2,
          "text": "多環境"
        },
        {
          "level": 2,
          "text": "CI/CD 整合"
        },
        {
          "level": 2,
          "text": "心法"
        }
      ]
    }
  ],
  "boss": {
    "name": "容器巨人",
    "hp": 250,
    "emoji": "🐋",
    "description": "Docker 是它的鱗片、Compose 是它的呼吸"
  },
  "quiz": {
    "id": "ch22-quiz",
    "questions": [],
    "xpReward": 50,
    "perfectBonus": 50
  }
}
